{
    "active_lock_reason": null,
    "assignee": null,
    "assignees": [],
    "author_association": "NONE",
    "body": "Thanks for the feedback! If your issue is related to the Flutter framework itself,\r\nplease open an issue at\r\n[github.com/flutter/flutter](https://github.com/flutter/flutter/issues/new).\r\n\r\n## Steps to Reproduce\r\n\r\n_Please tell us what you were doing and what went wrong_\r\n\r\n\r\n## Version info\r\n\r\nPlease paste the output of running `flutter doctor -v` here (available from the command\r\nline or from `Tools > Flutter > Flutter Doctor`). It will provide the version of the\r\nFlutter framework as well as of the IntelliJ plugin.\r\n",
    "closed_at": "2018-03-26T13:32:34Z",
    "comment_data": [
        {
            "author_association": "MEMBER",
            "body": "The quickest fix is probably to uninstall Flutter then follow the instructions here:\r\nhttps://flutter.io/setup-windows/\r\n",
            "created_at": "2018-03-26T13:32:34Z",
            "html_url": "https://github.com/flutter/flutter-intellij/issues/2002#issuecomment-376166862",
            "id": 376166862,
            "issue_url": "https://api.github.com/repos/flutter/flutter-intellij/issues/2002",
            "node_id": "MDEyOklzc3VlQ29tbWVudDM3NjE2Njg2Mg==",
            "performed_via_github_app": null,
            "reactions": {
                "+1": 0,
                "-1": 0,
                "confused": 0,
                "eyes": 0,
                "heart": 0,
                "hooray": 0,
                "laugh": 0,
                "rocket": 0,
                "total_count": 0,
                "url": "https://api.github.com/repos/flutter/flutter-intellij/issues/comments/376166862/reactions"
            },
            "updated_at": "2018-03-26T13:32:34Z",
            "url": "https://api.github.com/repos/flutter/flutter-intellij/issues/comments/376166862",
            "user": {
                "avatar_url": "https://avatars.githubusercontent.com/u/8518285?v=4",
                "events_url": "https://api.github.com/users/stevemessick/events{/privacy}",
                "followers_url": "https://api.github.com/users/stevemessick/followers",
                "following_url": "https://api.github.com/users/stevemessick/following{/other_user}",
                "gists_url": "https://api.github.com/users/stevemessick/gists{/gist_id}",
                "gravatar_id": "",
                "html_url": "https://github.com/stevemessick",
                "id": 8518285,
                "login": "stevemessick",
                "node_id": "MDQ6VXNlcjg1MTgyODU=",
                "organizations_url": "https://api.github.com/users/stevemessick/orgs",
                "received_events_url": "https://api.github.com/users/stevemessick/received_events",
                "repos_url": "https://api.github.com/users/stevemessick/repos",
                "site_admin": false,
                "starred_url": "https://api.github.com/users/stevemessick/starred{/owner}{/repo}",
                "subscriptions_url": "https://api.github.com/users/stevemessick/subscriptions",
                "type": "User",
                "url": "https://api.github.com/users/stevemessick"
            }
        }
    ],
    "comments": 1,
    "comments_url": "https://api.github.com/repos/flutter/flutter-intellij/issues/2002/comments",
    "created_at": "2018-03-24T17:59:38Z",
    "event_data": [
        {
            "actor": {
                "avatar_url": "https://avatars.githubusercontent.com/u/8518285?v=4",
                "events_url": "https://api.github.com/users/stevemessick/events{/privacy}",
                "followers_url": "https://api.github.com/users/stevemessick/followers",
                "following_url": "https://api.github.com/users/stevemessick/following{/other_user}",
                "gists_url": "https://api.github.com/users/stevemessick/gists{/gist_id}",
                "gravatar_id": "",
                "html_url": "https://github.com/stevemessick",
                "id": 8518285,
                "login": "stevemessick",
                "node_id": "MDQ6VXNlcjg1MTgyODU=",
                "organizations_url": "https://api.github.com/users/stevemessick/orgs",
                "received_events_url": "https://api.github.com/users/stevemessick/received_events",
                "repos_url": "https://api.github.com/users/stevemessick/repos",
                "site_admin": false,
                "starred_url": "https://api.github.com/users/stevemessick/starred{/owner}{/repo}",
                "subscriptions_url": "https://api.github.com/users/stevemessick/subscriptions",
                "type": "User",
                "url": "https://api.github.com/users/stevemessick"
            },
            "commit_id": null,
            "commit_url": null,
            "created_at": "2018-03-26T13:32:34Z",
            "event": "closed",
            "id": 1540861332,
            "node_id": "MDExOkNsb3NlZEV2ZW50MTU0MDg2MTMzMg==",
            "performed_via_github_app": null,
            "state_reason": null,
            "url": "https://api.github.com/repos/flutter/flutter-intellij/issues/events/1540861332"
        }
    ],
    "events_url": "https://api.github.com/repos/flutter/flutter-intellij/issues/2002/events",
    "html_url": "https://github.com/flutter/flutter-intellij/issues/2002",
    "id": 308284755,
    "labels": [],
    "labels_url": "https://api.github.com/repos/flutter/flutter-intellij/issues/2002/labels{/name}",
    "locked": false,
    "milestone": null,
    "node_id": "MDU6SXNzdWUzMDgyODQ3NTU=",
    "number": 2002,
    "performed_via_github_app": null,
    "reactions": {
        "+1": 0,
        "-1": 0,
        "confused": 0,
        "eyes": 0,
        "heart": 0,
        "hooray": 0,
        "laugh": 0,
        "rocket": 0,
        "total_count": 0,
        "url": "https://api.github.com/repos/flutter/flutter-intellij/issues/2002/reactions"
    },
    "repository_url": "https://api.github.com/repos/flutter/flutter-intellij",
    "state": "closed",
    "state_reason": "completed",
    "timeline_url": "https://api.github.com/repos/flutter/flutter-intellij/issues/2002/timeline",
    "title": "while trying to run my first app i was getting Unable to locate a development device; please run 'flutter doctor' for information about installing additional components.  error in android studio console and running the flutter doctor in command prompt it is showing   Doctor summary (to see all details, run flutter doctor -v): [√] Flutter (Channel beta, v0.1.5, on Microsoft Windows [Version 10.0.16299.309], locale en-IN) [!] Android toolchain - develop for Android devices (Android SDK 26.0.2)     X Android SDK file not found: C:\\Android\\platforms\\android-27\\android.jar. [√] Android Studio (version 3.0) [!] VS Code (version 1.20.0) [√] Connected devices (1 available) is it neccasary to install sdk 27 ",
    "updated_at": "2018-03-26T13:32:34Z",
    "url": "https://api.github.com/repos/flutter/flutter-intellij/issues/2002",
    "user": {
        "avatar_url": "https://avatars.githubusercontent.com/u/25244865?v=4",
        "events_url": "https://api.github.com/users/vivekanandasuggu/events{/privacy}",
        "followers_url": "https://api.github.com/users/vivekanandasuggu/followers",
        "following_url": "https://api.github.com/users/vivekanandasuggu/following{/other_user}",
        "gists_url": "https://api.github.com/users/vivekanandasuggu/gists{/gist_id}",
        "gravatar_id": "",
        "html_url": "https://github.com/vivekanandasuggu",
        "id": 25244865,
        "login": "vivekanandasuggu",
        "node_id": "MDQ6VXNlcjI1MjQ0ODY1",
        "organizations_url": "https://api.github.com/users/vivekanandasuggu/orgs",
        "received_events_url": "https://api.github.com/users/vivekanandasuggu/received_events",
        "repos_url": "https://api.github.com/users/vivekanandasuggu/repos",
        "site_admin": false,
        "starred_url": "https://api.github.com/users/vivekanandasuggu/starred{/owner}{/repo}",
        "subscriptions_url": "https://api.github.com/users/vivekanandasuggu/subscriptions",
        "type": "User",
        "url": "https://api.github.com/users/vivekanandasuggu"
    }
}