{
    "active_lock_reason": null,
    "assignee": null,
    "assignees": [],
    "author_association": "CONTRIBUTOR",
    "body": "(For inspiration we could look at the dev tools console.)\r\n",
    "closed_at": "2020-01-07T20:46:35Z",
    "comment_data": [
        {
            "author_association": "CONTRIBUTOR",
            "body": "@pq, could you explain more ?\r\n",
            "created_at": "2018-09-09T06:45:45Z",
            "html_url": "https://github.com/flutter/flutter-intellij/issues/2588#issuecomment-419694815",
            "id": 419694815,
            "issue_url": "https://api.github.com/repos/flutter/flutter-intellij/issues/2588",
            "node_id": "MDEyOklzc3VlQ29tbWVudDQxOTY5NDgxNQ==",
            "performed_via_github_app": null,
            "reactions": {
                "+1": 0,
                "-1": 0,
                "confused": 0,
                "eyes": 0,
                "heart": 0,
                "hooray": 0,
                "laugh": 0,
                "rocket": 0,
                "total_count": 0,
                "url": "https://api.github.com/repos/flutter/flutter-intellij/issues/comments/419694815/reactions"
            },
            "updated_at": "2018-09-09T06:45:45Z",
            "url": "https://api.github.com/repos/flutter/flutter-intellij/issues/comments/419694815",
            "user": {
                "avatar_url": "https://avatars.githubusercontent.com/u/6185205?v=4",
                "events_url": "https://api.github.com/users/quangson91/events{/privacy}",
                "followers_url": "https://api.github.com/users/quangson91/followers",
                "following_url": "https://api.github.com/users/quangson91/following{/other_user}",
                "gists_url": "https://api.github.com/users/quangson91/gists{/gist_id}",
                "gravatar_id": "",
                "html_url": "https://github.com/quangson91",
                "id": 6185205,
                "login": "quangson91",
                "node_id": "MDQ6VXNlcjYxODUyMDU=",
                "organizations_url": "https://api.github.com/users/quangson91/orgs",
                "received_events_url": "https://api.github.com/users/quangson91/received_events",
                "repos_url": "https://api.github.com/users/quangson91/repos",
                "site_admin": false,
                "starred_url": "https://api.github.com/users/quangson91/starred{/owner}{/repo}",
                "subscriptions_url": "https://api.github.com/users/quangson91/subscriptions",
                "type": "User",
                "url": "https://api.github.com/users/quangson91"
            }
        },
        {
            "author_association": "CONTRIBUTOR",
            "body": "Sure.  When the same message is repeated, it would be nice to have only one entry but with a count of occurrences.  For example, the dev console does it like this:\r\n\r\n![image](https://user-images.githubusercontent.com/67586/45268271-4b529a00-b42e-11e8-888a-5444cc4ebfc7.png)\r\n",
            "created_at": "2018-09-09T19:46:58Z",
            "html_url": "https://github.com/flutter/flutter-intellij/issues/2588#issuecomment-419740091",
            "id": 419740091,
            "issue_url": "https://api.github.com/repos/flutter/flutter-intellij/issues/2588",
            "node_id": "MDEyOklzc3VlQ29tbWVudDQxOTc0MDA5MQ==",
            "performed_via_github_app": null,
            "reactions": {
                "+1": 0,
                "-1": 0,
                "confused": 0,
                "eyes": 0,
                "heart": 0,
                "hooray": 0,
                "laugh": 0,
                "rocket": 0,
                "total_count": 0,
                "url": "https://api.github.com/repos/flutter/flutter-intellij/issues/comments/419740091/reactions"
            },
            "updated_at": "2018-09-09T19:46:58Z",
            "url": "https://api.github.com/repos/flutter/flutter-intellij/issues/comments/419740091",
            "user": {
                "avatar_url": "https://avatars.githubusercontent.com/u/67586?v=4",
                "events_url": "https://api.github.com/users/pq/events{/privacy}",
                "followers_url": "https://api.github.com/users/pq/followers",
                "following_url": "https://api.github.com/users/pq/following{/other_user}",
                "gists_url": "https://api.github.com/users/pq/gists{/gist_id}",
                "gravatar_id": "",
                "html_url": "https://github.com/pq",
                "id": 67586,
                "login": "pq",
                "node_id": "MDQ6VXNlcjY3NTg2",
                "organizations_url": "https://api.github.com/users/pq/orgs",
                "received_events_url": "https://api.github.com/users/pq/received_events",
                "repos_url": "https://api.github.com/users/pq/repos",
                "site_admin": false,
                "starred_url": "https://api.github.com/users/pq/starred{/owner}{/repo}",
                "subscriptions_url": "https://api.github.com/users/pq/subscriptions",
                "type": "User",
                "url": "https://api.github.com/users/pq"
            }
        },
        {
            "author_association": "CONTRIBUTOR",
            "body": "I understood. \r\nI will try to implement this :)\r\nThank you!\r\n",
            "created_at": "2018-09-09T23:42:50Z",
            "html_url": "https://github.com/flutter/flutter-intellij/issues/2588#issuecomment-419753749",
            "id": 419753749,
            "issue_url": "https://api.github.com/repos/flutter/flutter-intellij/issues/2588",
            "node_id": "MDEyOklzc3VlQ29tbWVudDQxOTc1Mzc0OQ==",
            "performed_via_github_app": null,
            "reactions": {
                "+1": 0,
                "-1": 0,
                "confused": 0,
                "eyes": 0,
                "heart": 0,
                "hooray": 1,
                "laugh": 0,
                "rocket": 0,
                "total_count": 1,
                "url": "https://api.github.com/repos/flutter/flutter-intellij/issues/comments/419753749/reactions"
            },
            "updated_at": "2018-09-09T23:42:50Z",
            "url": "https://api.github.com/repos/flutter/flutter-intellij/issues/comments/419753749",
            "user": {
                "avatar_url": "https://avatars.githubusercontent.com/u/6185205?v=4",
                "events_url": "https://api.github.com/users/quangson91/events{/privacy}",
                "followers_url": "https://api.github.com/users/quangson91/followers",
                "following_url": "https://api.github.com/users/quangson91/following{/other_user}",
                "gists_url": "https://api.github.com/users/quangson91/gists{/gist_id}",
                "gravatar_id": "",
                "html_url": "https://github.com/quangson91",
                "id": 6185205,
                "login": "quangson91",
                "node_id": "MDQ6VXNlcjYxODUyMDU=",
                "organizations_url": "https://api.github.com/users/quangson91/orgs",
                "received_events_url": "https://api.github.com/users/quangson91/received_events",
                "repos_url": "https://api.github.com/users/quangson91/repos",
                "site_admin": false,
                "starred_url": "https://api.github.com/users/quangson91/starred{/owner}{/repo}",
                "subscriptions_url": "https://api.github.com/users/quangson91/subscriptions",
                "type": "User",
                "url": "https://api.github.com/users/quangson91"
            }
        }
    ],
    "comments": 3,
    "comments_url": "https://api.github.com/repos/flutter/flutter-intellij/issues/2588/comments",
    "created_at": "2018-09-06T19:24:49Z",
    "event_data": [
        {
            "actor": {
                "avatar_url": "https://avatars.githubusercontent.com/u/67586?v=4",
                "events_url": "https://api.github.com/users/pq/events{/privacy}",
                "followers_url": "https://api.github.com/users/pq/followers",
                "following_url": "https://api.github.com/users/pq/following{/other_user}",
                "gists_url": "https://api.github.com/users/pq/gists{/gist_id}",
                "gravatar_id": "",
                "html_url": "https://github.com/pq",
                "id": 67586,
                "login": "pq",
                "node_id": "MDQ6VXNlcjY3NTg2",
                "organizations_url": "https://api.github.com/users/pq/orgs",
                "received_events_url": "https://api.github.com/users/pq/received_events",
                "repos_url": "https://api.github.com/users/pq/repos",
                "site_admin": false,
                "starred_url": "https://api.github.com/users/pq/starred{/owner}{/repo}",
                "subscriptions_url": "https://api.github.com/users/pq/subscriptions",
                "type": "User",
                "url": "https://api.github.com/users/pq"
            },
            "commit_id": null,
            "commit_url": null,
            "created_at": "2018-09-06T19:24:49Z",
            "event": "labeled",
            "id": 1831245339,
            "label": {
                "color": "f9b363",
                "name": "logging"
            },
            "node_id": "MDEyOkxhYmVsZWRFdmVudDE4MzEyNDUzMzk=",
            "performed_via_github_app": null,
            "url": "https://api.github.com/repos/flutter/flutter-intellij/issues/events/1831245339"
        },
        {
            "actor": {
                "avatar_url": "https://avatars.githubusercontent.com/u/67586?v=4",
                "events_url": "https://api.github.com/users/pq/events{/privacy}",
                "followers_url": "https://api.github.com/users/pq/followers",
                "following_url": "https://api.github.com/users/pq/following{/other_user}",
                "gists_url": "https://api.github.com/users/pq/gists{/gist_id}",
                "gravatar_id": "",
                "html_url": "https://github.com/pq",
                "id": 67586,
                "login": "pq",
                "node_id": "MDQ6VXNlcjY3NTg2",
                "organizations_url": "https://api.github.com/users/pq/orgs",
                "received_events_url": "https://api.github.com/users/pq/received_events",
                "repos_url": "https://api.github.com/users/pq/repos",
                "site_admin": false,
                "starred_url": "https://api.github.com/users/pq/starred{/owner}{/repo}",
                "subscriptions_url": "https://api.github.com/users/pq/subscriptions",
                "type": "User",
                "url": "https://api.github.com/users/pq"
            },
            "commit_id": null,
            "commit_url": null,
            "created_at": "2018-09-06T19:24:55Z",
            "event": "labeled",
            "id": 1831245612,
            "label": {
                "color": "84b6eb",
                "name": "enhancement"
            },
            "node_id": "MDEyOkxhYmVsZWRFdmVudDE4MzEyNDU2MTI=",
            "performed_via_github_app": null,
            "url": "https://api.github.com/repos/flutter/flutter-intellij/issues/events/1831245612"
        },
        {
            "actor": {
                "avatar_url": "https://avatars.githubusercontent.com/u/67586?v=4",
                "events_url": "https://api.github.com/users/pq/events{/privacy}",
                "followers_url": "https://api.github.com/users/pq/followers",
                "following_url": "https://api.github.com/users/pq/following{/other_user}",
                "gists_url": "https://api.github.com/users/pq/gists{/gist_id}",
                "gravatar_id": "",
                "html_url": "https://github.com/pq",
                "id": 67586,
                "login": "pq",
                "node_id": "MDQ6VXNlcjY3NTg2",
                "organizations_url": "https://api.github.com/users/pq/orgs",
                "received_events_url": "https://api.github.com/users/pq/received_events",
                "repos_url": "https://api.github.com/users/pq/repos",
                "site_admin": false,
                "starred_url": "https://api.github.com/users/pq/starred{/owner}{/repo}",
                "subscriptions_url": "https://api.github.com/users/pq/subscriptions",
                "type": "User",
                "url": "https://api.github.com/users/pq"
            },
            "commit_id": null,
            "commit_url": null,
            "created_at": "2018-09-06T19:24:59Z",
            "event": "milestoned",
            "id": 1831245729,
            "milestone": {
                "title": "Backlog"
            },
            "node_id": "MDE1Ok1pbGVzdG9uZWRFdmVudDE4MzEyNDU3Mjk=",
            "performed_via_github_app": null,
            "url": "https://api.github.com/repos/flutter/flutter-intellij/issues/events/1831245729"
        },
        {
            "actor": {
                "avatar_url": "https://avatars.githubusercontent.com/u/67586?v=4",
                "events_url": "https://api.github.com/users/pq/events{/privacy}",
                "followers_url": "https://api.github.com/users/pq/followers",
                "following_url": "https://api.github.com/users/pq/following{/other_user}",
                "gists_url": "https://api.github.com/users/pq/gists{/gist_id}",
                "gravatar_id": "",
                "html_url": "https://github.com/pq",
                "id": 67586,
                "login": "pq",
                "node_id": "MDQ6VXNlcjY3NTg2",
                "organizations_url": "https://api.github.com/users/pq/orgs",
                "received_events_url": "https://api.github.com/users/pq/received_events",
                "repos_url": "https://api.github.com/users/pq/repos",
                "site_admin": false,
                "starred_url": "https://api.github.com/users/pq/starred{/owner}{/repo}",
                "subscriptions_url": "https://api.github.com/users/pq/subscriptions",
                "type": "User",
                "url": "https://api.github.com/users/pq"
            },
            "commit_id": null,
            "commit_url": null,
            "created_at": "2018-09-09T06:45:45Z",
            "event": "mentioned",
            "id": 1834472907,
            "node_id": "MDE0Ok1lbnRpb25lZEV2ZW50MTgzNDQ3MjkwNw==",
            "performed_via_github_app": null,
            "url": "https://api.github.com/repos/flutter/flutter-intellij/issues/events/1834472907"
        },
        {
            "actor": {
                "avatar_url": "https://avatars.githubusercontent.com/u/67586?v=4",
                "events_url": "https://api.github.com/users/pq/events{/privacy}",
                "followers_url": "https://api.github.com/users/pq/followers",
                "following_url": "https://api.github.com/users/pq/following{/other_user}",
                "gists_url": "https://api.github.com/users/pq/gists{/gist_id}",
                "gravatar_id": "",
                "html_url": "https://github.com/pq",
                "id": 67586,
                "login": "pq",
                "node_id": "MDQ6VXNlcjY3NTg2",
                "organizations_url": "https://api.github.com/users/pq/orgs",
                "received_events_url": "https://api.github.com/users/pq/received_events",
                "repos_url": "https://api.github.com/users/pq/repos",
                "site_admin": false,
                "starred_url": "https://api.github.com/users/pq/starred{/owner}{/repo}",
                "subscriptions_url": "https://api.github.com/users/pq/subscriptions",
                "type": "User",
                "url": "https://api.github.com/users/pq"
            },
            "commit_id": null,
            "commit_url": null,
            "created_at": "2018-09-09T06:45:45Z",
            "event": "subscribed",
            "id": 1834472909,
            "node_id": "MDE1OlN1YnNjcmliZWRFdmVudDE4MzQ0NzI5MDk=",
            "performed_via_github_app": null,
            "url": "https://api.github.com/repos/flutter/flutter-intellij/issues/events/1834472909"
        },
        {
            "actor": {
                "avatar_url": "https://avatars.githubusercontent.com/u/1269969?v=4",
                "events_url": "https://api.github.com/users/devoncarew/events{/privacy}",
                "followers_url": "https://api.github.com/users/devoncarew/followers",
                "following_url": "https://api.github.com/users/devoncarew/following{/other_user}",
                "gists_url": "https://api.github.com/users/devoncarew/gists{/gist_id}",
                "gravatar_id": "",
                "html_url": "https://github.com/devoncarew",
                "id": 1269969,
                "login": "devoncarew",
                "node_id": "MDQ6VXNlcjEyNjk5Njk=",
                "organizations_url": "https://api.github.com/users/devoncarew/orgs",
                "received_events_url": "https://api.github.com/users/devoncarew/received_events",
                "repos_url": "https://api.github.com/users/devoncarew/repos",
                "site_admin": false,
                "starred_url": "https://api.github.com/users/devoncarew/starred{/owner}{/repo}",
                "subscriptions_url": "https://api.github.com/users/devoncarew/subscriptions",
                "type": "User",
                "url": "https://api.github.com/users/devoncarew"
            },
            "commit_id": null,
            "commit_url": null,
            "created_at": "2020-01-07T20:46:35Z",
            "event": "closed",
            "id": 2929002199,
            "node_id": "MDExOkNsb3NlZEV2ZW50MjkyOTAwMjE5OQ==",
            "performed_via_github_app": null,
            "state_reason": null,
            "url": "https://api.github.com/repos/flutter/flutter-intellij/issues/events/2929002199"
        }
    ],
    "events_url": "https://api.github.com/repos/flutter/flutter-intellij/issues/2588/events",
    "html_url": "https://github.com/flutter/flutter-intellij/issues/2588",
    "id": 357792197,
    "labels": [
        {
            "color": "84b6eb",
            "default": true,
            "description": null,
            "id": 414053718,
            "name": "enhancement",
            "node_id": "MDU6TGFiZWw0MTQwNTM3MTg=",
            "url": "https://api.github.com/repos/flutter/flutter-intellij/labels/enhancement"
        },
        {
            "color": "f9b363",
            "default": false,
            "description": "",
            "id": 922767962,
            "name": "logging",
            "node_id": "MDU6TGFiZWw5MjI3Njc5NjI=",
            "url": "https://api.github.com/repos/flutter/flutter-intellij/labels/logging"
        }
    ],
    "labels_url": "https://api.github.com/repos/flutter/flutter-intellij/issues/2588/labels{/name}",
    "locked": false,
    "milestone": {
        "closed_at": null,
        "closed_issues": 272,
        "created_at": "2016-11-02T16:47:43Z",
        "creator": {
            "avatar_url": "https://avatars.githubusercontent.com/u/67586?v=4",
            "events_url": "https://api.github.com/users/pq/events{/privacy}",
            "followers_url": "https://api.github.com/users/pq/followers",
            "following_url": "https://api.github.com/users/pq/following{/other_user}",
            "gists_url": "https://api.github.com/users/pq/gists{/gist_id}",
            "gravatar_id": "",
            "html_url": "https://github.com/pq",
            "id": 67586,
            "login": "pq",
            "node_id": "MDQ6VXNlcjY3NTg2",
            "organizations_url": "https://api.github.com/users/pq/orgs",
            "received_events_url": "https://api.github.com/users/pq/received_events",
            "repos_url": "https://api.github.com/users/pq/repos",
            "site_admin": false,
            "starred_url": "https://api.github.com/users/pq/starred{/owner}{/repo}",
            "subscriptions_url": "https://api.github.com/users/pq/subscriptions",
            "type": "User",
            "url": "https://api.github.com/users/pq"
        },
        "description": "Work triaged but not yet planned for a specific release.",
        "due_on": null,
        "html_url": "https://github.com/flutter/flutter-intellij/milestone/10",
        "id": 2110115,
        "labels_url": "https://api.github.com/repos/flutter/flutter-intellij/milestones/10/labels",
        "node_id": "MDk6TWlsZXN0b25lMjExMDExNQ==",
        "number": 10,
        "open_issues": 243,
        "state": "open",
        "title": "Backlog",
        "updated_at": "2022-09-30T16:42:45Z",
        "url": "https://api.github.com/repos/flutter/flutter-intellij/milestones/10"
    },
    "node_id": "MDU6SXNzdWUzNTc3OTIxOTc=",
    "number": 2588,
    "performed_via_github_app": null,
    "reactions": {
        "+1": 0,
        "-1": 0,
        "confused": 0,
        "eyes": 0,
        "heart": 0,
        "hooray": 0,
        "laugh": 0,
        "rocket": 0,
        "total_count": 0,
        "url": "https://api.github.com/repos/flutter/flutter-intellij/issues/2588/reactions"
    },
    "repository_url": "https://api.github.com/repos/flutter/flutter-intellij",
    "state": "closed",
    "state_reason": "completed",
    "timeline_url": "https://api.github.com/repos/flutter/flutter-intellij/issues/2588/timeline",
    "title": "Consolidate (and count) repeated logging messages.",
    "updated_at": "2020-01-07T20:46:36Z",
    "url": "https://api.github.com/repos/flutter/flutter-intellij/issues/2588",
    "user": {
        "avatar_url": "https://avatars.githubusercontent.com/u/67586?v=4",
        "events_url": "https://api.github.com/users/pq/events{/privacy}",
        "followers_url": "https://api.github.com/users/pq/followers",
        "following_url": "https://api.github.com/users/pq/following{/other_user}",
        "gists_url": "https://api.github.com/users/pq/gists{/gist_id}",
        "gravatar_id": "",
        "html_url": "https://github.com/pq",
        "id": 67586,
        "login": "pq",
        "node_id": "MDQ6VXNlcjY3NTg2",
        "organizations_url": "https://api.github.com/users/pq/orgs",
        "received_events_url": "https://api.github.com/users/pq/received_events",
        "repos_url": "https://api.github.com/users/pq/repos",
        "site_admin": false,
        "starred_url": "https://api.github.com/users/pq/starred{/owner}{/repo}",
        "subscriptions_url": "https://api.github.com/users/pq/subscriptions",
        "type": "User",
        "url": "https://api.github.com/users/pq"
    }
}