{
    "active_lock_reason": null,
    "assignee": null,
    "assignees": [],
    "author_association": "CONTRIBUTOR",
    "body": "When visiting apptree, this one came up.  Easy to repro.\r\n\r\n1. Set a breakpoint.\r\n2. When paused, evaluate an expression.\r\n3. Exception is thrown.\r\n\r\nTo get back to a happy state we need to restart the analysis server.\r\n\r\n\r\n\r\nAnalyzer Feedback from IntelliJ\r\n\r\n# Version information\r\n\r\n- `IDEA 183.2940.10`\r\n- `2.1.0-edge.4cf2d3990bac1f1df2f524899e1560a3683f3133`\r\n- `IU-183.2940.10, JRE 1.8.0_151-b12x64 Oracle Corporation, OS Mac OS X(x86_64) v10.13.6, screens 1680x1050  Retina`\r\n\r\n# Exception\r\n\r\n```\r\nDart analysis server, SDK version 2.1.0-edge.4cf2d3990bac1f1df2f524899e1560a3683f3133, server version 1.20.5, FATAL error: Failed to handle request: {id: 2622, method: execution.getSuggestions, params: {code: con, offset: 3, contextFile: /Users/pquitslund/IdeaProjects/fplugin_proj/lib/main.dart, contextOffset: 2154, variables: [], expressions: []}, clientRequestTime: 1538435427635}\r\nInconsistentAnalysisException: Requested result might be inconsistent with previously returned results\r\n\r\n#0      AnalysisSessionImpl._checkConsistency (package:analyzer/src/dart/analysis/session.dart:156:7)\r\n#1      AnalysisSessionImpl.getResolvedAst (package:analyzer/src/dart/analysis/session.dart:121:5)\r\n#2      DartChangeBuilderImpl.createFileEditBuilder (package:analyzer_plugin/src/utilities/change_builder/change_builder_dart.dart:58:42)\r\n<asynchronous suspension>\r\n#3      ChangeBuilderImpl.addFileEdit (package:analyzer_plugin/src/utilities/change_builder/change_builder_core.dart:68:41)\r\n<asynchronous suspension>\r\n#4      DartChangeBuilderImpl.addFileEdit (package:analyzer_plugin/src/utilities/change_builder/change_builder_dart.dart:47:18)\r\n#5      RuntimeCompletionComputer.compute (package:analysis_server/src/domains/execution/completion.dart:59:25)\r\n<asynchronous suspension>\r\n#6      ExecutionDomainHandler.getSuggestions (package:analysis_server/src/domain_execution.dart:79:63)\r\n<asynchronous suspension>\r\n#7      ExecutionDomainHandler.handleRequest (package:analysis_server/src/domain_execution.dart:97:9)\r\n#8      AnalysisServer.handleRequest.<anonymous closure>.<anonymous closure> (package:analysis_server/src/analysis_server.dart:750:45)\r\n#9      _PerformanceTagImpl.makeCurrentWhile (package:analyzer/src/generated/utilities_general.dart:210:15)\r\n#10     AnalysisServer.handleRequest.<anonymous closure> (package:analysis_server/src/analysis_server.dart:746:50)\r\n#11     _rootRun (dart:async/zone.dart:1124:13)\r\n#12     _CustomZone.run (dart:async/zone.dart:1021:19)\r\n#13     _runZoned (dart:async/zone.dart:1516:10)\r\n#14     runZoned (dart:async/zone.dart:1500:12)\r\n#15     AnalysisServer.handleRequest (package:analysis_server/src/analysis_server.dart:745:5)\r\n#16     ByteStreamServerChannel._readRequest.<anonymous closure> (package:analysis_server/src/channel/byte_stream_channel.dart:174:16)\r\n#17     _PerformanceTagImpl.makeCurrentWhile (package:analyzer/src/generated/utilities_general.dart:210:15)\r\n#18     ByteStreamServerChannel._readRequest (package:analysis_server/src/channel/byte_stream_channel.dart:165:47)\r\n#19     ByteStreamServerChannel.listen.<anonymous closure> (package:analysis_server/src/channel/byte_stream_channel.dart:110:26)\r\n#20     _rootRunUnary (dart:async/zone.dart:1132:38)\r\n#21     _CustomZone.runUnary (dart:async/zone.dart:1029:19)\r\n#22     _CustomZone.runUnaryGuarded (dart:async/zone.dart:931:7)\r\n#23     _BufferingStreamSubscription._sendData (dart:async/stream_impl.dart:336:11)\r\n#24     _BufferingStreamSubscription._add (dart:async/stream_impl.dart:263:7)\r\n#25     _SinkTransformerStreamSubscription._add (dart:async/stream_transformers.dart:68:11)\r\n#26     _EventSinkWrapper.add (dart:async/stream_transformers.dart:15:11)\r\n#27     _StringAdapterSink.add (dart:convert/string_conversion.dart:268:11)\r\n#28     _LineSplitterSink._addLines (dart:convert/line_splitter.dart:154:13)\r\n#29     _LineSplitterSink.addSlice (dart:convert/line_splitter.dart:129:5)\r\n#30     StringConversionSinkMixin.add (dart:convert/string_conversion.dart:189:5)\r\n#31     _SinkTransformerStreamSubscription._handleData (dart:async/stream_transformers.dart:120:24)\r\n#32     _rootRunUnary (dart:async/zone.dart:1132:38)\r\n#33     _CustomZone.runUnary (dart:async/zone.dart:1029:19)\r\n#34     _CustomZone.runUnaryGuarded (dart:async/zone.dart:931:7)\r\n#35     _BufferingStreamSubscription._sendData (dart:async/stream_impl.dart:336:11)\r\n#36     _BufferingStreamSubscription._add (dart:async/stream_impl.dart:263:7)\r\n#37     _SinkTransformerStreamSubscription._add (dart:async/stream_transformers.dart:68:11)\r\n#38     _EventSinkWrapper.add (dart:async/stream_transformers.dart:15:11)\r\n#39     _StringAdapterSink.add (dart:convert/string_conversion.dart:268:11)\r\n#40     _StringAdapterSink.addSlice (dart:convert/string_conversion.dart:273:7)\r\n#41     _Utf8ConversionSink.addSlice (dart:convert/string_conversion.dart:348:20)\r\n#42     _Utf8ConversionSink.add (dart:convert/string_conversion.dart:341:5)\r\n#43     _ConverterStreamEventSink.add (dart:convert/chunked_conversion.dart:86:18)\r\n#44     _SinkTransformerStreamSubscription._handleData (dart:async/stream_transformers.dart:120:24)\r\n#45     _rootRunUnary (dart:async/zone.dart:1132:38)\r\n#46     _CustomZone.runUnary (dart:async/zone.dart:1029:19)\r\n#47     _CustomZone.runUnaryGuarded (dart:async/zone.dart:931:7)\r\n#48     _BufferingStreamSubscription._sendData (dart:async/stream_impl.dart:336:11)\r\n#49     _BufferingStreamSubscription._add (dart:async/stream_impl.dart:263:7)\r\n#50     _SyncStreamController._sendData (dart:async/stream_controller.dart:763:19)\r\n#51     _StreamController._add (dart:async/stream_controller.dart:639:7)\r\n#52     _StreamController.add (dart:async/stream_controller.dart:585:5)\r\n#53     _Socket._onData (dart:io/runtime/binsocket_patch.dart:1714:41)\r\n#54     _rootRunUnary (dart:async/zone.dart:1136:13)\r\n#55     _CustomZone.runUnary (dart:async/zone.dart:1029:19)\r\n#56     _CustomZone.runUnaryGuarded (dart:async/zone.dart:931:7)\r\n#57     _BufferingStreamSubscription._sendData (dart:async/stream_impl.dart:336:11)\r\n#58     _BufferingStreamSubscription._add (dart:async/stream_impl.dart:263:7)\r\n#59     _SyncStreamController._sendData (dart:async/stream_controller.dart:763:19)\r\n#60     _StreamController._add (dart:async/stream_controller.dart:639:7)\r\n#61     _StreamController.add (dart:async/stream_controller.dart:585:5)\r\n#62     new _RawSocket.<anonymous closure> (dart:io/runtime/binsocket_patch.dart:1276:33)\r\n#63     _NativeSocket.issueReadEvent.issue (dart:io/runtime/binsocket_patch.dart:819:14)\r\n#64     _microtaskLoop (dart:async/schedule_microtask.dart:41:21)\r\n#65     _startMicrotaskLoop (dart:async/schedule_microtask.dart:50:5)\r\n#66     _runPendingImmediateCallback (dart:isolate/runtime/libisolate_patch.dart:115:13)\r\n#67     _RawReceivePortImpl._handleMessage (dart:isolate/runtime/libisolate_patch.dart:172:5)\r\n```\r\n\r\n```\r\n1538435427461 => {\"id\":\"2621\",\"method\":\"execution.getSuggestions\",\"params\":{\"code\":\"co\",\"offset\":2,\"contextFile\":\"/Users/pquitslund/IdeaProjects/fplugin_proj/lib/main.dart\",\"contextOffset\":2154,\"varia\r\n1538435427629 <= {\"id\":\"2620\",\"result\":{\"suggestions\":[{\"kind\":\"INVOCATION\",\"relevance\":1000,\"completion\":\"Codec\",\"selectionOffset\":5,\"selectionLength\":0,\"isDeprecated\":false,\"isPotential\":false,\"docS\r\n1538435427632 <= {\"event\":\"analysis.highlights\",\"params\":{\"file\":\"/Users/pquitslund/IdeaProjects/fplugin_proj/lib/main.dart\",\"regions\":[{\"type\":\"DIRECTIVE\",\"offset\":0,\"length\":22},{\"type\":\"BUILT_IN\",\"\r\n1538435427632 <= {\"event\":\"analysis.navigation\",\"params\":{\"file\":\"/Users/pquitslund/IdeaProjects/fplugin_proj/lib/main.dart\",\"regions\":[{\"offset\":7,\"length\":14,\"targets\":[0]},{\"offset\":31,\"length\":31,\r\n1538435427632 <= {\"event\":\"analysis.closingLabels\",\"params\":{\"file\":\"/Users/pquitslund/IdeaProjects/fplugin_proj/lib/main.dart\",\"labels\":[{\"offset\":1292,\"length\":52,\"label\":\"MaterialApp\"},{\"offset\":22\r\n1538435427632 <= {\"event\":\"analysis.outline\",\"params\":{\"file\":\"/Users/pquitslund/IdeaProjects/fplugin_proj/lib/main.dart\",\"kind\":\"LIBRARY\",\"outline\":{\"element\":{\"kind\":\"COMPILATION_UNIT\",\"name\":\"<unit\r\n1538435427632 <= {\"event\":\"analysis.overrides\",\"params\":{\"file\":\"/Users/pquitslund/IdeaProjects/fplugin_proj/lib/main.dart\",\"overrides\":[{\"offset\":1220,\"length\":5,\"superclassMember\":{\"element\":{\"kind\"\r\n1538435427635 => {\"id\":\"2622\",\"method\":\"execution.getSuggestions\",\"params\":{\"code\":\"con\",\"offset\":3,\"contextFile\":\"/Users/pquitslund/IdeaProjects/fplugin_proj/lib/main.dart\",\"contextOffset\":2154,\"vari\r\n1538435427660 <= {\"event\":\"analysis.errors\",\"params\":{\"file\":\"/Users/pquitslund/IdeaProjects/fplugin_proj/lib/main.dart\",\"errors\":[{\"severity\":\"INFO\",\"type\":\"LINT\",\"location\":{\"file\":\"/Users/pquitslun\r\n1538435427661 <= {\"event\":\"analysis.highlights\",\"params\":{\"file\":\"/Users/pquitslund/IdeaProjects/fplugin_proj/lib/main.dart\",\"regions\":[{\"type\":\"DIRECTIVE\",\"offset\":0,\"length\":22},{\"type\":\"BUILT_IN\",\"\r\n1538435427662 <= {\"event\":\"analysis.navigation\",\"params\":{\"file\":\"/Users/pquitslund/IdeaProjects/fplugin_proj/lib/main.dart\",\"regions\":[{\"offset\":7,\"length\":14,\"targets\":[0]},{\"offset\":31,\"length\":31,\r\n1538435427662 <= {\"event\":\"analysis.closingLabels\",\"params\":{\"file\":\"/Users/pquitslund/IdeaProjects/fplugin_proj/lib/main.dart\",\"labels\":[{\"offset\":1292,\"length\":52,\"label\":\"MaterialApp\"},{\"offset\":22\r\n1538435427663 <= {\"event\":\"analysis.outline\",\"params\":{\"file\":\"/Users/pquitslund/IdeaProjects/fplugin_proj/lib/main.dart\",\"kind\":\"LIBRARY\",\"outline\":{\"element\":{\"kind\":\"COMPILATION_UNIT\",\"name\":\"<unit\r\n1538435427663 <= {\"event\":\"analysis.overrides\",\"params\":{\"file\":\"/Users/pquitslund/IdeaProjects/fplugin_proj/lib/main.dart\",\"overrides\":[{\"offset\":1220,\"length\":5,\"superclassMember\":{\"element\":{\"kind\"\r\n1538435427702 <= {\"event\":\"analysis.errors\",\"params\":{\"file\":\"/Users/pquitslund/IdeaProjects/fplugin_proj/lib/main.dart\",\"errors\":[{\"severity\":\"INFO\",\"type\":\"LINT\",\"location\":{\"file\":\"/Users/pquitslun\r\n1538435427709 <= {\"event\":\"server.error\",\"params\":{\"isFatal\":true,\"message\":\"Failed to handle request: {id: 2622, method: execution.getSuggestions, params: {code: con, offset: 3, contextFile: /Users/p\r\n1538435427895 <= {\"id\":\"2621\",\"result\":{\"suggestions\":[{\"kind\":\"INVOCATION\",\"relevance\":1000,\"completion\":\"Codec\",\"selectionOffset\":5,\"selectionLength\":0,\"isDeprecated\":false,\"isPotential\":false,\"docS\r\n1538435427897 <= {\"event\":\"analysis.highlights\",\"params\":{\"file\":\"/Users/pquitslund/IdeaProjects/fplugin_proj/lib/main.dart\",\"regions\":[{\"type\":\"DIRECTIVE\",\"offset\":0,\"length\":22},{\"type\":\"BUILT_IN\",\"\r\n1538435427897 <= {\"event\":\"analysis.navigation\",\"params\":{\"file\":\"/Users/pquitslund/IdeaProjects/fplugin_proj/lib/main.dart\",\"regions\":[{\"offset\":7,\"length\":14,\"targets\":[0]},{\"offset\":31,\"length\":31,\r\n1538435427898 <= {\"event\":\"analysis.closingLabels\",\"params\":{\"file\":\"/Users/pquitslund/IdeaProjects/fplugin_proj/lib/main.dart\",\"labels\":[{\"offset\":1292,\"length\":52,\"label\":\"MaterialApp\"},{\"offset\":22\r\n1538435427898 <= {\"event\":\"analysis.outline\",\"params\":{\"file\":\"/Users/pquitslund/IdeaProjects/fplugin_proj/lib/main.dart\",\"kind\":\"LIBRARY\",\"outline\":{\"element\":{\"kind\":\"COMPILATION_UNIT\",\"name\":\"<unit\r\n1538435427899 <= {\"event\":\"analysis.overrides\",\"params\":{\"file\":\"/Users/pquitslund/IdeaProjects/fplugin_proj/lib/main.dart\",\"overrides\":[{\"offset\":1220,\"length\":5,\"superclassMember\":{\"element\":{\"kind\"\r\n1538435427942 <= {\"event\":\"analysis.errors\",\"params\":{\"file\":\"/Users/pquitslund/IdeaProjects/fplugin_proj/lib/main.dart\",\"errors\":[{\"severity\":\"INFO\",\"type\":\"LINT\",\"location\":{\"file\":\"/Users/pquitslun\r\n1538435427943 <= {\"event\":\"analysis.highlights\",\"params\":{\"file\":\"/Users/pquitslund/IdeaProjects/fplugin_proj/lib/main.dart\",\"regions\":[{\"type\":\"DIRECTIVE\",\"offset\":0,\"length\":22},{\"type\":\"BUILT_IN\",\"\r\n1538435427944 <= {\"event\":\"analysis.navigation\",\"params\":{\"file\":\"/Users/pquitslund/IdeaProjects/fplugin_proj/lib/main.dart\",\"regions\":[{\"offset\":7,\"length\":14,\"targets\":[0]},{\"offset\":31,\"length\":31,\r\n1538435427944 <= {\"event\":\"analysis.closingLabels\",\"params\":{\"file\":\"/Users/pquitslund/IdeaProjects/fplugin_proj/lib/main.dart\",\"labels\":[{\"offset\":1292,\"length\":52,\"label\":\"MaterialApp\"},{\"offset\":22\r\n1538435427944 <= {\"event\":\"analysis.outline\",\"params\":{\"file\":\"/Users/pquitslund/IdeaProjects/fplugin_proj/lib/main.dart\",\"kind\":\"LIBRARY\",\"outline\":{\"element\":{\"kind\":\"COMPILATION_UNIT\",\"name\":\"<unit\r\n1538435427945 <= {\"event\":\"analysis.overrides\",\"params\":{\"file\":\"/Users/pquitslund/IdeaProjects/fplugin_proj/lib/main.dart\",\"overrides\":[{\"offset\":1220,\"length\":5,\"superclassMember\":{\"element\":{\"kind\"\r\n1538435427946 <= {\"event\":\"server.status\",\"params\":{\"analysis\":{\"isAnalyzing\":false}}}\r\n1538435427947 <= {\"event\":\"analysis.implemented\",\"params\":{\"file\":\"/Users/pquitslund/IdeaProjects/fplugin_proj/lib/main.dart\",\"classes\":[],\"members\":[]}}\r\n```\r\n\r\n/cc @jacob314 @bwilkerson @devoncarew ",
    "closed_at": "2018-10-02T18:08:52Z",
    "comment_data": [
        {
            "author_association": "CONTRIBUTOR",
            "body": "/cc @matthewtsmith @johnpryan",
            "created_at": "2018-10-01T23:29:12Z",
            "html_url": "https://github.com/flutter/flutter-intellij/issues/2647#issuecomment-426097265",
            "id": 426097265,
            "issue_url": "https://api.github.com/repos/flutter/flutter-intellij/issues/2647",
            "node_id": "MDEyOklzc3VlQ29tbWVudDQyNjA5NzI2NQ==",
            "performed_via_github_app": null,
            "reactions": {
                "+1": 0,
                "-1": 0,
                "confused": 0,
                "eyes": 0,
                "heart": 0,
                "hooray": 0,
                "laugh": 0,
                "rocket": 0,
                "total_count": 0,
                "url": "https://api.github.com/repos/flutter/flutter-intellij/issues/comments/426097265/reactions"
            },
            "updated_at": "2018-10-01T23:29:12Z",
            "url": "https://api.github.com/repos/flutter/flutter-intellij/issues/comments/426097265",
            "user": {
                "avatar_url": "https://avatars.githubusercontent.com/u/67586?v=4",
                "events_url": "https://api.github.com/users/pq/events{/privacy}",
                "followers_url": "https://api.github.com/users/pq/followers",
                "following_url": "https://api.github.com/users/pq/following{/other_user}",
                "gists_url": "https://api.github.com/users/pq/gists{/gist_id}",
                "gravatar_id": "",
                "html_url": "https://github.com/pq",
                "id": 67586,
                "login": "pq",
                "node_id": "MDQ6VXNlcjY3NTg2",
                "organizations_url": "https://api.github.com/users/pq/orgs",
                "received_events_url": "https://api.github.com/users/pq/received_events",
                "repos_url": "https://api.github.com/users/pq/repos",
                "site_admin": false,
                "starred_url": "https://api.github.com/users/pq/starred{/owner}{/repo}",
                "subscriptions_url": "https://api.github.com/users/pq/subscriptions",
                "type": "User",
                "url": "https://api.github.com/users/pq"
            }
        },
        {
            "author_association": "CONTRIBUTOR",
            "body": "@scheglov any ideas?",
            "created_at": "2018-10-02T01:55:23Z",
            "html_url": "https://github.com/flutter/flutter-intellij/issues/2647#issuecomment-426120783",
            "id": 426120783,
            "issue_url": "https://api.github.com/repos/flutter/flutter-intellij/issues/2647",
            "node_id": "MDEyOklzc3VlQ29tbWVudDQyNjEyMDc4Mw==",
            "performed_via_github_app": null,
            "reactions": {
                "+1": 0,
                "-1": 0,
                "confused": 0,
                "eyes": 0,
                "heart": 0,
                "hooray": 0,
                "laugh": 0,
                "rocket": 0,
                "total_count": 0,
                "url": "https://api.github.com/repos/flutter/flutter-intellij/issues/comments/426120783/reactions"
            },
            "updated_at": "2018-10-02T01:55:23Z",
            "url": "https://api.github.com/repos/flutter/flutter-intellij/issues/comments/426120783",
            "user": {
                "avatar_url": "https://avatars.githubusercontent.com/u/1226812?v=4",
                "events_url": "https://api.github.com/users/jacob314/events{/privacy}",
                "followers_url": "https://api.github.com/users/jacob314/followers",
                "following_url": "https://api.github.com/users/jacob314/following{/other_user}",
                "gists_url": "https://api.github.com/users/jacob314/gists{/gist_id}",
                "gravatar_id": "",
                "html_url": "https://github.com/jacob314",
                "id": 1226812,
                "login": "jacob314",
                "node_id": "MDQ6VXNlcjEyMjY4MTI=",
                "organizations_url": "https://api.github.com/users/jacob314/orgs",
                "received_events_url": "https://api.github.com/users/jacob314/received_events",
                "repos_url": "https://api.github.com/users/jacob314/repos",
                "site_admin": false,
                "starred_url": "https://api.github.com/users/jacob314/starred{/owner}{/repo}",
                "subscriptions_url": "https://api.github.com/users/jacob314/subscriptions",
                "type": "User",
                "url": "https://api.github.com/users/jacob314"
            }
        },
        {
            "author_association": "CONTRIBUTOR",
            "body": "I've seen this myself a couple times.\r\nUnfortunately I didn't have time to implement a proper fix yet.",
            "created_at": "2018-10-02T01:58:24Z",
            "html_url": "https://github.com/flutter/flutter-intellij/issues/2647#issuecomment-426121260",
            "id": 426121260,
            "issue_url": "https://api.github.com/repos/flutter/flutter-intellij/issues/2647",
            "node_id": "MDEyOklzc3VlQ29tbWVudDQyNjEyMTI2MA==",
            "performed_via_github_app": null,
            "reactions": {
                "+1": 0,
                "-1": 0,
                "confused": 0,
                "eyes": 0,
                "heart": 0,
                "hooray": 0,
                "laugh": 0,
                "rocket": 0,
                "total_count": 0,
                "url": "https://api.github.com/repos/flutter/flutter-intellij/issues/comments/426121260/reactions"
            },
            "updated_at": "2018-10-02T01:58:24Z",
            "url": "https://api.github.com/repos/flutter/flutter-intellij/issues/comments/426121260",
            "user": {
                "avatar_url": "https://avatars.githubusercontent.com/u/384794?v=4",
                "events_url": "https://api.github.com/users/scheglov/events{/privacy}",
                "followers_url": "https://api.github.com/users/scheglov/followers",
                "following_url": "https://api.github.com/users/scheglov/following{/other_user}",
                "gists_url": "https://api.github.com/users/scheglov/gists{/gist_id}",
                "gravatar_id": "",
                "html_url": "https://github.com/scheglov",
                "id": 384794,
                "login": "scheglov",
                "node_id": "MDQ6VXNlcjM4NDc5NA==",
                "organizations_url": "https://api.github.com/users/scheglov/orgs",
                "received_events_url": "https://api.github.com/users/scheglov/received_events",
                "repos_url": "https://api.github.com/users/scheglov/repos",
                "site_admin": false,
                "starred_url": "https://api.github.com/users/scheglov/starred{/owner}{/repo}",
                "subscriptions_url": "https://api.github.com/users/scheglov/subscriptions",
                "type": "User",
                "url": "https://api.github.com/users/scheglov"
            }
        },
        {
            "author_association": "CONTRIBUTOR",
            "body": "As another point of reference: you can get back to a happy place by editing and re-saving the file.\r\n\r\n> Unfortunately I didn't have time to implement a proper fix yet.\r\n\r\nIs this a fix here or in the dart plugin?",
            "created_at": "2018-10-02T18:03:36Z",
            "html_url": "https://github.com/flutter/flutter-intellij/issues/2647#issuecomment-426373192",
            "id": 426373192,
            "issue_url": "https://api.github.com/repos/flutter/flutter-intellij/issues/2647",
            "node_id": "MDEyOklzc3VlQ29tbWVudDQyNjM3MzE5Mg==",
            "performed_via_github_app": null,
            "reactions": {
                "+1": 0,
                "-1": 0,
                "confused": 0,
                "eyes": 0,
                "heart": 0,
                "hooray": 0,
                "laugh": 0,
                "rocket": 0,
                "total_count": 0,
                "url": "https://api.github.com/repos/flutter/flutter-intellij/issues/comments/426373192/reactions"
            },
            "updated_at": "2018-10-02T18:03:36Z",
            "url": "https://api.github.com/repos/flutter/flutter-intellij/issues/comments/426373192",
            "user": {
                "avatar_url": "https://avatars.githubusercontent.com/u/67586?v=4",
                "events_url": "https://api.github.com/users/pq/events{/privacy}",
                "followers_url": "https://api.github.com/users/pq/followers",
                "following_url": "https://api.github.com/users/pq/following{/other_user}",
                "gists_url": "https://api.github.com/users/pq/gists{/gist_id}",
                "gravatar_id": "",
                "html_url": "https://github.com/pq",
                "id": 67586,
                "login": "pq",
                "node_id": "MDQ6VXNlcjY3NTg2",
                "organizations_url": "https://api.github.com/users/pq/orgs",
                "received_events_url": "https://api.github.com/users/pq/received_events",
                "repos_url": "https://api.github.com/users/pq/repos",
                "site_admin": false,
                "starred_url": "https://api.github.com/users/pq/starred{/owner}{/repo}",
                "subscriptions_url": "https://api.github.com/users/pq/subscriptions",
                "type": "User",
                "url": "https://api.github.com/users/pq"
            }
        },
        {
            "author_association": "CONTRIBUTOR",
            "body": "It should be fixed in Analysis Server.\r\nAPI and the Dart plugin are fine.",
            "created_at": "2018-10-02T18:05:26Z",
            "html_url": "https://github.com/flutter/flutter-intellij/issues/2647#issuecomment-426373796",
            "id": 426373796,
            "issue_url": "https://api.github.com/repos/flutter/flutter-intellij/issues/2647",
            "node_id": "MDEyOklzc3VlQ29tbWVudDQyNjM3Mzc5Ng==",
            "performed_via_github_app": null,
            "reactions": {
                "+1": 0,
                "-1": 0,
                "confused": 0,
                "eyes": 0,
                "heart": 0,
                "hooray": 0,
                "laugh": 0,
                "rocket": 0,
                "total_count": 0,
                "url": "https://api.github.com/repos/flutter/flutter-intellij/issues/comments/426373796/reactions"
            },
            "updated_at": "2018-10-02T18:05:26Z",
            "url": "https://api.github.com/repos/flutter/flutter-intellij/issues/comments/426373796",
            "user": {
                "avatar_url": "https://avatars.githubusercontent.com/u/384794?v=4",
                "events_url": "https://api.github.com/users/scheglov/events{/privacy}",
                "followers_url": "https://api.github.com/users/scheglov/followers",
                "following_url": "https://api.github.com/users/scheglov/following{/other_user}",
                "gists_url": "https://api.github.com/users/scheglov/gists{/gist_id}",
                "gravatar_id": "",
                "html_url": "https://github.com/scheglov",
                "id": 384794,
                "login": "scheglov",
                "node_id": "MDQ6VXNlcjM4NDc5NA==",
                "organizations_url": "https://api.github.com/users/scheglov/orgs",
                "received_events_url": "https://api.github.com/users/scheglov/received_events",
                "repos_url": "https://api.github.com/users/scheglov/repos",
                "site_admin": false,
                "starred_url": "https://api.github.com/users/scheglov/starred{/owner}{/repo}",
                "subscriptions_url": "https://api.github.com/users/scheglov/subscriptions",
                "type": "User",
                "url": "https://api.github.com/users/scheglov"
            }
        },
        {
            "author_association": "CONTRIBUTOR",
            "body": "OK, great.  Should I move this to the SDK?",
            "created_at": "2018-10-02T18:06:40Z",
            "html_url": "https://github.com/flutter/flutter-intellij/issues/2647#issuecomment-426374208",
            "id": 426374208,
            "issue_url": "https://api.github.com/repos/flutter/flutter-intellij/issues/2647",
            "node_id": "MDEyOklzc3VlQ29tbWVudDQyNjM3NDIwOA==",
            "performed_via_github_app": null,
            "reactions": {
                "+1": 0,
                "-1": 0,
                "confused": 0,
                "eyes": 0,
                "heart": 0,
                "hooray": 0,
                "laugh": 0,
                "rocket": 0,
                "total_count": 0,
                "url": "https://api.github.com/repos/flutter/flutter-intellij/issues/comments/426374208/reactions"
            },
            "updated_at": "2018-10-02T18:06:40Z",
            "url": "https://api.github.com/repos/flutter/flutter-intellij/issues/comments/426374208",
            "user": {
                "avatar_url": "https://avatars.githubusercontent.com/u/67586?v=4",
                "events_url": "https://api.github.com/users/pq/events{/privacy}",
                "followers_url": "https://api.github.com/users/pq/followers",
                "following_url": "https://api.github.com/users/pq/following{/other_user}",
                "gists_url": "https://api.github.com/users/pq/gists{/gist_id}",
                "gravatar_id": "",
                "html_url": "https://github.com/pq",
                "id": 67586,
                "login": "pq",
                "node_id": "MDQ6VXNlcjY3NTg2",
                "organizations_url": "https://api.github.com/users/pq/orgs",
                "received_events_url": "https://api.github.com/users/pq/received_events",
                "repos_url": "https://api.github.com/users/pq/repos",
                "site_admin": false,
                "starred_url": "https://api.github.com/users/pq/starred{/owner}{/repo}",
                "subscriptions_url": "https://api.github.com/users/pq/subscriptions",
                "type": "User",
                "url": "https://api.github.com/users/pq"
            }
        },
        {
            "author_association": "CONTRIBUTOR",
            "body": "Sounds right to me.",
            "created_at": "2018-10-02T18:07:46Z",
            "html_url": "https://github.com/flutter/flutter-intellij/issues/2647#issuecomment-426374578",
            "id": 426374578,
            "issue_url": "https://api.github.com/repos/flutter/flutter-intellij/issues/2647",
            "node_id": "MDEyOklzc3VlQ29tbWVudDQyNjM3NDU3OA==",
            "performed_via_github_app": null,
            "reactions": {
                "+1": 0,
                "-1": 0,
                "confused": 0,
                "eyes": 0,
                "heart": 0,
                "hooray": 0,
                "laugh": 0,
                "rocket": 0,
                "total_count": 0,
                "url": "https://api.github.com/repos/flutter/flutter-intellij/issues/comments/426374578/reactions"
            },
            "updated_at": "2018-10-02T18:07:46Z",
            "url": "https://api.github.com/repos/flutter/flutter-intellij/issues/comments/426374578",
            "user": {
                "avatar_url": "https://avatars.githubusercontent.com/u/384794?v=4",
                "events_url": "https://api.github.com/users/scheglov/events{/privacy}",
                "followers_url": "https://api.github.com/users/scheglov/followers",
                "following_url": "https://api.github.com/users/scheglov/following{/other_user}",
                "gists_url": "https://api.github.com/users/scheglov/gists{/gist_id}",
                "gravatar_id": "",
                "html_url": "https://github.com/scheglov",
                "id": 384794,
                "login": "scheglov",
                "node_id": "MDQ6VXNlcjM4NDc5NA==",
                "organizations_url": "https://api.github.com/users/scheglov/orgs",
                "received_events_url": "https://api.github.com/users/scheglov/received_events",
                "repos_url": "https://api.github.com/users/scheglov/repos",
                "site_admin": false,
                "starred_url": "https://api.github.com/users/scheglov/starred{/owner}{/repo}",
                "subscriptions_url": "https://api.github.com/users/scheglov/subscriptions",
                "type": "User",
                "url": "https://api.github.com/users/scheglov"
            }
        },
        {
            "author_association": "CONTRIBUTOR",
            "body": "This issue was moved to dart-lang/sdk#34646",
            "created_at": "2018-10-02T18:08:52Z",
            "html_url": "https://github.com/flutter/flutter-intellij/issues/2647#issuecomment-426374965",
            "id": 426374965,
            "issue_url": "https://api.github.com/repos/flutter/flutter-intellij/issues/2647",
            "node_id": "MDEyOklzc3VlQ29tbWVudDQyNjM3NDk2NQ==",
            "performed_via_github_app": null,
            "reactions": {
                "+1": 0,
                "-1": 0,
                "confused": 0,
                "eyes": 0,
                "heart": 0,
                "hooray": 0,
                "laugh": 0,
                "rocket": 0,
                "total_count": 0,
                "url": "https://api.github.com/repos/flutter/flutter-intellij/issues/comments/426374965/reactions"
            },
            "updated_at": "2018-10-02T18:08:52Z",
            "url": "https://api.github.com/repos/flutter/flutter-intellij/issues/comments/426374965",
            "user": {
                "avatar_url": "https://avatars.githubusercontent.com/u/67586?v=4",
                "events_url": "https://api.github.com/users/pq/events{/privacy}",
                "followers_url": "https://api.github.com/users/pq/followers",
                "following_url": "https://api.github.com/users/pq/following{/other_user}",
                "gists_url": "https://api.github.com/users/pq/gists{/gist_id}",
                "gravatar_id": "",
                "html_url": "https://github.com/pq",
                "id": 67586,
                "login": "pq",
                "node_id": "MDQ6VXNlcjY3NTg2",
                "organizations_url": "https://api.github.com/users/pq/orgs",
                "received_events_url": "https://api.github.com/users/pq/received_events",
                "repos_url": "https://api.github.com/users/pq/repos",
                "site_admin": false,
                "starred_url": "https://api.github.com/users/pq/starred{/owner}{/repo}",
                "subscriptions_url": "https://api.github.com/users/pq/subscriptions",
                "type": "User",
                "url": "https://api.github.com/users/pq"
            }
        }
    ],
    "comments": 8,
    "comments_url": "https://api.github.com/repos/flutter/flutter-intellij/issues/2647/comments",
    "created_at": "2018-10-01T23:16:47Z",
    "event_data": [
        {
            "actor": {
                "avatar_url": "https://avatars.githubusercontent.com/u/67586?v=4",
                "events_url": "https://api.github.com/users/pq/events{/privacy}",
                "followers_url": "https://api.github.com/users/pq/followers",
                "following_url": "https://api.github.com/users/pq/following{/other_user}",
                "gists_url": "https://api.github.com/users/pq/gists{/gist_id}",
                "gravatar_id": "",
                "html_url": "https://github.com/pq",
                "id": 67586,
                "login": "pq",
                "node_id": "MDQ6VXNlcjY3NTg2",
                "organizations_url": "https://api.github.com/users/pq/orgs",
                "received_events_url": "https://api.github.com/users/pq/received_events",
                "repos_url": "https://api.github.com/users/pq/repos",
                "site_admin": false,
                "starred_url": "https://api.github.com/users/pq/starred{/owner}{/repo}",
                "subscriptions_url": "https://api.github.com/users/pq/subscriptions",
                "type": "User",
                "url": "https://api.github.com/users/pq"
            },
            "commit_id": null,
            "commit_url": null,
            "created_at": "2018-10-01T23:16:47Z",
            "event": "labeled",
            "id": 1878034483,
            "label": {
                "color": "ee0701",
                "name": "bug"
            },
            "node_id": "MDEyOkxhYmVsZWRFdmVudDE4NzgwMzQ0ODM=",
            "performed_via_github_app": null,
            "url": "https://api.github.com/repos/flutter/flutter-intellij/issues/events/1878034483"
        },
        {
            "actor": {
                "avatar_url": "https://avatars.githubusercontent.com/u/67586?v=4",
                "events_url": "https://api.github.com/users/pq/events{/privacy}",
                "followers_url": "https://api.github.com/users/pq/followers",
                "following_url": "https://api.github.com/users/pq/following{/other_user}",
                "gists_url": "https://api.github.com/users/pq/gists{/gist_id}",
                "gravatar_id": "",
                "html_url": "https://github.com/pq",
                "id": 67586,
                "login": "pq",
                "node_id": "MDQ6VXNlcjY3NTg2",
                "organizations_url": "https://api.github.com/users/pq/orgs",
                "received_events_url": "https://api.github.com/users/pq/received_events",
                "repos_url": "https://api.github.com/users/pq/repos",
                "site_admin": false,
                "starred_url": "https://api.github.com/users/pq/starred{/owner}{/repo}",
                "subscriptions_url": "https://api.github.com/users/pq/subscriptions",
                "type": "User",
                "url": "https://api.github.com/users/pq"
            },
            "commit_id": null,
            "commit_url": null,
            "created_at": "2018-10-01T23:16:47Z",
            "event": "milestoned",
            "id": 1878034484,
            "milestone": {
                "title": "On Deck"
            },
            "node_id": "MDE1Ok1pbGVzdG9uZWRFdmVudDE4NzgwMzQ0ODQ=",
            "performed_via_github_app": null,
            "url": "https://api.github.com/repos/flutter/flutter-intellij/issues/events/1878034484"
        },
        {
            "actor": {
                "avatar_url": "https://avatars.githubusercontent.com/u/1226812?v=4",
                "events_url": "https://api.github.com/users/jacob314/events{/privacy}",
                "followers_url": "https://api.github.com/users/jacob314/followers",
                "following_url": "https://api.github.com/users/jacob314/following{/other_user}",
                "gists_url": "https://api.github.com/users/jacob314/gists{/gist_id}",
                "gravatar_id": "",
                "html_url": "https://github.com/jacob314",
                "id": 1226812,
                "login": "jacob314",
                "node_id": "MDQ6VXNlcjEyMjY4MTI=",
                "organizations_url": "https://api.github.com/users/jacob314/orgs",
                "received_events_url": "https://api.github.com/users/jacob314/received_events",
                "repos_url": "https://api.github.com/users/jacob314/repos",
                "site_admin": false,
                "starred_url": "https://api.github.com/users/jacob314/starred{/owner}{/repo}",
                "subscriptions_url": "https://api.github.com/users/jacob314/subscriptions",
                "type": "User",
                "url": "https://api.github.com/users/jacob314"
            },
            "commit_id": null,
            "commit_url": null,
            "created_at": "2018-10-01T23:16:47Z",
            "event": "mentioned",
            "id": 1878034489,
            "node_id": "MDE0Ok1lbnRpb25lZEV2ZW50MTg3ODAzNDQ4OQ==",
            "performed_via_github_app": null,
            "url": "https://api.github.com/repos/flutter/flutter-intellij/issues/events/1878034489"
        },
        {
            "actor": {
                "avatar_url": "https://avatars.githubusercontent.com/u/1226812?v=4",
                "events_url": "https://api.github.com/users/jacob314/events{/privacy}",
                "followers_url": "https://api.github.com/users/jacob314/followers",
                "following_url": "https://api.github.com/users/jacob314/following{/other_user}",
                "gists_url": "https://api.github.com/users/jacob314/gists{/gist_id}",
                "gravatar_id": "",
                "html_url": "https://github.com/jacob314",
                "id": 1226812,
                "login": "jacob314",
                "node_id": "MDQ6VXNlcjEyMjY4MTI=",
                "organizations_url": "https://api.github.com/users/jacob314/orgs",
                "received_events_url": "https://api.github.com/users/jacob314/received_events",
                "repos_url": "https://api.github.com/users/jacob314/repos",
                "site_admin": false,
                "starred_url": "https://api.github.com/users/jacob314/starred{/owner}{/repo}",
                "subscriptions_url": "https://api.github.com/users/jacob314/subscriptions",
                "type": "User",
                "url": "https://api.github.com/users/jacob314"
            },
            "commit_id": null,
            "commit_url": null,
            "created_at": "2018-10-01T23:16:47Z",
            "event": "subscribed",
            "id": 1878034492,
            "node_id": "MDE1OlN1YnNjcmliZWRFdmVudDE4NzgwMzQ0OTI=",
            "performed_via_github_app": null,
            "url": "https://api.github.com/repos/flutter/flutter-intellij/issues/events/1878034492"
        },
        {
            "actor": {
                "avatar_url": "https://avatars.githubusercontent.com/u/1269969?v=4",
                "events_url": "https://api.github.com/users/devoncarew/events{/privacy}",
                "followers_url": "https://api.github.com/users/devoncarew/followers",
                "following_url": "https://api.github.com/users/devoncarew/following{/other_user}",
                "gists_url": "https://api.github.com/users/devoncarew/gists{/gist_id}",
                "gravatar_id": "",
                "html_url": "https://github.com/devoncarew",
                "id": 1269969,
                "login": "devoncarew",
                "node_id": "MDQ6VXNlcjEyNjk5Njk=",
                "organizations_url": "https://api.github.com/users/devoncarew/orgs",
                "received_events_url": "https://api.github.com/users/devoncarew/received_events",
                "repos_url": "https://api.github.com/users/devoncarew/repos",
                "site_admin": false,
                "starred_url": "https://api.github.com/users/devoncarew/starred{/owner}{/repo}",
                "subscriptions_url": "https://api.github.com/users/devoncarew/subscriptions",
                "type": "User",
                "url": "https://api.github.com/users/devoncarew"
            },
            "commit_id": null,
            "commit_url": null,
            "created_at": "2018-10-01T23:16:47Z",
            "event": "mentioned",
            "id": 1878034495,
            "node_id": "MDE0Ok1lbnRpb25lZEV2ZW50MTg3ODAzNDQ5NQ==",
            "performed_via_github_app": null,
            "url": "https://api.github.com/repos/flutter/flutter-intellij/issues/events/1878034495"
        },
        {
            "actor": {
                "avatar_url": "https://avatars.githubusercontent.com/u/1269969?v=4",
                "events_url": "https://api.github.com/users/devoncarew/events{/privacy}",
                "followers_url": "https://api.github.com/users/devoncarew/followers",
                "following_url": "https://api.github.com/users/devoncarew/following{/other_user}",
                "gists_url": "https://api.github.com/users/devoncarew/gists{/gist_id}",
                "gravatar_id": "",
                "html_url": "https://github.com/devoncarew",
                "id": 1269969,
                "login": "devoncarew",
                "node_id": "MDQ6VXNlcjEyNjk5Njk=",
                "organizations_url": "https://api.github.com/users/devoncarew/orgs",
                "received_events_url": "https://api.github.com/users/devoncarew/received_events",
                "repos_url": "https://api.github.com/users/devoncarew/repos",
                "site_admin": false,
                "starred_url": "https://api.github.com/users/devoncarew/starred{/owner}{/repo}",
                "subscriptions_url": "https://api.github.com/users/devoncarew/subscriptions",
                "type": "User",
                "url": "https://api.github.com/users/devoncarew"
            },
            "commit_id": null,
            "commit_url": null,
            "created_at": "2018-10-01T23:16:47Z",
            "event": "subscribed",
            "id": 1878034498,
            "node_id": "MDE1OlN1YnNjcmliZWRFdmVudDE4NzgwMzQ0OTg=",
            "performed_via_github_app": null,
            "url": "https://api.github.com/repos/flutter/flutter-intellij/issues/events/1878034498"
        },
        {
            "actor": {
                "avatar_url": "https://avatars.githubusercontent.com/u/5840555?v=4",
                "events_url": "https://api.github.com/users/bwilkerson/events{/privacy}",
                "followers_url": "https://api.github.com/users/bwilkerson/followers",
                "following_url": "https://api.github.com/users/bwilkerson/following{/other_user}",
                "gists_url": "https://api.github.com/users/bwilkerson/gists{/gist_id}",
                "gravatar_id": "",
                "html_url": "https://github.com/bwilkerson",
                "id": 5840555,
                "login": "bwilkerson",
                "node_id": "MDQ6VXNlcjU4NDA1NTU=",
                "organizations_url": "https://api.github.com/users/bwilkerson/orgs",
                "received_events_url": "https://api.github.com/users/bwilkerson/received_events",
                "repos_url": "https://api.github.com/users/bwilkerson/repos",
                "site_admin": false,
                "starred_url": "https://api.github.com/users/bwilkerson/starred{/owner}{/repo}",
                "subscriptions_url": "https://api.github.com/users/bwilkerson/subscriptions",
                "type": "User",
                "url": "https://api.github.com/users/bwilkerson"
            },
            "commit_id": null,
            "commit_url": null,
            "created_at": "2018-10-01T23:16:47Z",
            "event": "mentioned",
            "id": 1878034500,
            "node_id": "MDE0Ok1lbnRpb25lZEV2ZW50MTg3ODAzNDUwMA==",
            "performed_via_github_app": null,
            "url": "https://api.github.com/repos/flutter/flutter-intellij/issues/events/1878034500"
        },
        {
            "actor": {
                "avatar_url": "https://avatars.githubusercontent.com/u/5840555?v=4",
                "events_url": "https://api.github.com/users/bwilkerson/events{/privacy}",
                "followers_url": "https://api.github.com/users/bwilkerson/followers",
                "following_url": "https://api.github.com/users/bwilkerson/following{/other_user}",
                "gists_url": "https://api.github.com/users/bwilkerson/gists{/gist_id}",
                "gravatar_id": "",
                "html_url": "https://github.com/bwilkerson",
                "id": 5840555,
                "login": "bwilkerson",
                "node_id": "MDQ6VXNlcjU4NDA1NTU=",
                "organizations_url": "https://api.github.com/users/bwilkerson/orgs",
                "received_events_url": "https://api.github.com/users/bwilkerson/received_events",
                "repos_url": "https://api.github.com/users/bwilkerson/repos",
                "site_admin": false,
                "starred_url": "https://api.github.com/users/bwilkerson/starred{/owner}{/repo}",
                "subscriptions_url": "https://api.github.com/users/bwilkerson/subscriptions",
                "type": "User",
                "url": "https://api.github.com/users/bwilkerson"
            },
            "commit_id": null,
            "commit_url": null,
            "created_at": "2018-10-01T23:16:47Z",
            "event": "subscribed",
            "id": 1878034501,
            "node_id": "MDE1OlN1YnNjcmliZWRFdmVudDE4NzgwMzQ1MDE=",
            "performed_via_github_app": null,
            "url": "https://api.github.com/repos/flutter/flutter-intellij/issues/events/1878034501"
        },
        {
            "actor": {
                "avatar_url": "https://avatars.githubusercontent.com/u/1145719?v=4",
                "events_url": "https://api.github.com/users/johnpryan/events{/privacy}",
                "followers_url": "https://api.github.com/users/johnpryan/followers",
                "following_url": "https://api.github.com/users/johnpryan/following{/other_user}",
                "gists_url": "https://api.github.com/users/johnpryan/gists{/gist_id}",
                "gravatar_id": "",
                "html_url": "https://github.com/johnpryan",
                "id": 1145719,
                "login": "johnpryan",
                "node_id": "MDQ6VXNlcjExNDU3MTk=",
                "organizations_url": "https://api.github.com/users/johnpryan/orgs",
                "received_events_url": "https://api.github.com/users/johnpryan/received_events",
                "repos_url": "https://api.github.com/users/johnpryan/repos",
                "site_admin": false,
                "starred_url": "https://api.github.com/users/johnpryan/starred{/owner}{/repo}",
                "subscriptions_url": "https://api.github.com/users/johnpryan/subscriptions",
                "type": "User",
                "url": "https://api.github.com/users/johnpryan"
            },
            "commit_id": null,
            "commit_url": null,
            "created_at": "2018-10-01T23:29:12Z",
            "event": "mentioned",
            "id": 1878049420,
            "node_id": "MDE0Ok1lbnRpb25lZEV2ZW50MTg3ODA0OTQyMA==",
            "performed_via_github_app": null,
            "url": "https://api.github.com/repos/flutter/flutter-intellij/issues/events/1878049420"
        },
        {
            "actor": {
                "avatar_url": "https://avatars.githubusercontent.com/u/1145719?v=4",
                "events_url": "https://api.github.com/users/johnpryan/events{/privacy}",
                "followers_url": "https://api.github.com/users/johnpryan/followers",
                "following_url": "https://api.github.com/users/johnpryan/following{/other_user}",
                "gists_url": "https://api.github.com/users/johnpryan/gists{/gist_id}",
                "gravatar_id": "",
                "html_url": "https://github.com/johnpryan",
                "id": 1145719,
                "login": "johnpryan",
                "node_id": "MDQ6VXNlcjExNDU3MTk=",
                "organizations_url": "https://api.github.com/users/johnpryan/orgs",
                "received_events_url": "https://api.github.com/users/johnpryan/received_events",
                "repos_url": "https://api.github.com/users/johnpryan/repos",
                "site_admin": false,
                "starred_url": "https://api.github.com/users/johnpryan/starred{/owner}{/repo}",
                "subscriptions_url": "https://api.github.com/users/johnpryan/subscriptions",
                "type": "User",
                "url": "https://api.github.com/users/johnpryan"
            },
            "commit_id": null,
            "commit_url": null,
            "created_at": "2018-10-01T23:29:12Z",
            "event": "subscribed",
            "id": 1878049421,
            "node_id": "MDE1OlN1YnNjcmliZWRFdmVudDE4NzgwNDk0MjE=",
            "performed_via_github_app": null,
            "url": "https://api.github.com/repos/flutter/flutter-intellij/issues/events/1878049421"
        },
        {
            "actor": {
                "avatar_url": "https://avatars.githubusercontent.com/u/9000800?v=4",
                "events_url": "https://api.github.com/users/matthewtsmith/events{/privacy}",
                "followers_url": "https://api.github.com/users/matthewtsmith/followers",
                "following_url": "https://api.github.com/users/matthewtsmith/following{/other_user}",
                "gists_url": "https://api.github.com/users/matthewtsmith/gists{/gist_id}",
                "gravatar_id": "",
                "html_url": "https://github.com/matthewtsmith",
                "id": 9000800,
                "login": "matthewtsmith",
                "node_id": "MDQ6VXNlcjkwMDA4MDA=",
                "organizations_url": "https://api.github.com/users/matthewtsmith/orgs",
                "received_events_url": "https://api.github.com/users/matthewtsmith/received_events",
                "repos_url": "https://api.github.com/users/matthewtsmith/repos",
                "site_admin": false,
                "starred_url": "https://api.github.com/users/matthewtsmith/starred{/owner}{/repo}",
                "subscriptions_url": "https://api.github.com/users/matthewtsmith/subscriptions",
                "type": "User",
                "url": "https://api.github.com/users/matthewtsmith"
            },
            "commit_id": null,
            "commit_url": null,
            "created_at": "2018-10-01T23:29:12Z",
            "event": "mentioned",
            "id": 1878049422,
            "node_id": "MDE0Ok1lbnRpb25lZEV2ZW50MTg3ODA0OTQyMg==",
            "performed_via_github_app": null,
            "url": "https://api.github.com/repos/flutter/flutter-intellij/issues/events/1878049422"
        },
        {
            "actor": {
                "avatar_url": "https://avatars.githubusercontent.com/u/9000800?v=4",
                "events_url": "https://api.github.com/users/matthewtsmith/events{/privacy}",
                "followers_url": "https://api.github.com/users/matthewtsmith/followers",
                "following_url": "https://api.github.com/users/matthewtsmith/following{/other_user}",
                "gists_url": "https://api.github.com/users/matthewtsmith/gists{/gist_id}",
                "gravatar_id": "",
                "html_url": "https://github.com/matthewtsmith",
                "id": 9000800,
                "login": "matthewtsmith",
                "node_id": "MDQ6VXNlcjkwMDA4MDA=",
                "organizations_url": "https://api.github.com/users/matthewtsmith/orgs",
                "received_events_url": "https://api.github.com/users/matthewtsmith/received_events",
                "repos_url": "https://api.github.com/users/matthewtsmith/repos",
                "site_admin": false,
                "starred_url": "https://api.github.com/users/matthewtsmith/starred{/owner}{/repo}",
                "subscriptions_url": "https://api.github.com/users/matthewtsmith/subscriptions",
                "type": "User",
                "url": "https://api.github.com/users/matthewtsmith"
            },
            "commit_id": null,
            "commit_url": null,
            "created_at": "2018-10-01T23:29:12Z",
            "event": "subscribed",
            "id": 1878049423,
            "node_id": "MDE1OlN1YnNjcmliZWRFdmVudDE4NzgwNDk0MjM=",
            "performed_via_github_app": null,
            "url": "https://api.github.com/repos/flutter/flutter-intellij/issues/events/1878049423"
        },
        {
            "actor": {
                "avatar_url": "https://avatars.githubusercontent.com/u/384794?v=4",
                "events_url": "https://api.github.com/users/scheglov/events{/privacy}",
                "followers_url": "https://api.github.com/users/scheglov/followers",
                "following_url": "https://api.github.com/users/scheglov/following{/other_user}",
                "gists_url": "https://api.github.com/users/scheglov/gists{/gist_id}",
                "gravatar_id": "",
                "html_url": "https://github.com/scheglov",
                "id": 384794,
                "login": "scheglov",
                "node_id": "MDQ6VXNlcjM4NDc5NA==",
                "organizations_url": "https://api.github.com/users/scheglov/orgs",
                "received_events_url": "https://api.github.com/users/scheglov/received_events",
                "repos_url": "https://api.github.com/users/scheglov/repos",
                "site_admin": false,
                "starred_url": "https://api.github.com/users/scheglov/starred{/owner}{/repo}",
                "subscriptions_url": "https://api.github.com/users/scheglov/subscriptions",
                "type": "User",
                "url": "https://api.github.com/users/scheglov"
            },
            "commit_id": null,
            "commit_url": null,
            "created_at": "2018-10-02T01:55:23Z",
            "event": "mentioned",
            "id": 1878199894,
            "node_id": "MDE0Ok1lbnRpb25lZEV2ZW50MTg3ODE5OTg5NA==",
            "performed_via_github_app": null,
            "url": "https://api.github.com/repos/flutter/flutter-intellij/issues/events/1878199894"
        },
        {
            "actor": {
                "avatar_url": "https://avatars.githubusercontent.com/u/384794?v=4",
                "events_url": "https://api.github.com/users/scheglov/events{/privacy}",
                "followers_url": "https://api.github.com/users/scheglov/followers",
                "following_url": "https://api.github.com/users/scheglov/following{/other_user}",
                "gists_url": "https://api.github.com/users/scheglov/gists{/gist_id}",
                "gravatar_id": "",
                "html_url": "https://github.com/scheglov",
                "id": 384794,
                "login": "scheglov",
                "node_id": "MDQ6VXNlcjM4NDc5NA==",
                "organizations_url": "https://api.github.com/users/scheglov/orgs",
                "received_events_url": "https://api.github.com/users/scheglov/received_events",
                "repos_url": "https://api.github.com/users/scheglov/repos",
                "site_admin": false,
                "starred_url": "https://api.github.com/users/scheglov/starred{/owner}{/repo}",
                "subscriptions_url": "https://api.github.com/users/scheglov/subscriptions",
                "type": "User",
                "url": "https://api.github.com/users/scheglov"
            },
            "commit_id": null,
            "commit_url": null,
            "created_at": "2018-10-02T01:55:23Z",
            "event": "subscribed",
            "id": 1878199895,
            "node_id": "MDE1OlN1YnNjcmliZWRFdmVudDE4NzgxOTk4OTU=",
            "performed_via_github_app": null,
            "url": "https://api.github.com/repos/flutter/flutter-intellij/issues/events/1878199895"
        },
        {
            "actor": {
                "avatar_url": "https://avatars.githubusercontent.com/u/67586?v=4",
                "events_url": "https://api.github.com/users/pq/events{/privacy}",
                "followers_url": "https://api.github.com/users/pq/followers",
                "following_url": "https://api.github.com/users/pq/following{/other_user}",
                "gists_url": "https://api.github.com/users/pq/gists{/gist_id}",
                "gravatar_id": "",
                "html_url": "https://github.com/pq",
                "id": 67586,
                "login": "pq",
                "node_id": "MDQ6VXNlcjY3NTg2",
                "organizations_url": "https://api.github.com/users/pq/orgs",
                "received_events_url": "https://api.github.com/users/pq/received_events",
                "repos_url": "https://api.github.com/users/pq/repos",
                "site_admin": false,
                "starred_url": "https://api.github.com/users/pq/starred{/owner}{/repo}",
                "subscriptions_url": "https://api.github.com/users/pq/subscriptions",
                "type": "User",
                "url": "https://api.github.com/users/pq"
            },
            "commit_id": null,
            "commit_url": null,
            "created_at": "2018-10-02T18:08:53Z",
            "event": "closed",
            "id": 1880048828,
            "node_id": "MDExOkNsb3NlZEV2ZW50MTg4MDA0ODgyOA==",
            "performed_via_github_app": null,
            "state_reason": null,
            "url": "https://api.github.com/repos/flutter/flutter-intellij/issues/events/1880048828"
        }
    ],
    "events_url": "https://api.github.com/repos/flutter/flutter-intellij/issues/2647/events",
    "html_url": "https://github.com/flutter/flutter-intellij/issues/2647",
    "id": 365679550,
    "labels": [
        {
            "color": "ee0701",
            "default": true,
            "description": null,
            "id": 414053716,
            "name": "bug",
            "node_id": "MDU6TGFiZWw0MTQwNTM3MTY=",
            "url": "https://api.github.com/repos/flutter/flutter-intellij/labels/bug"
        }
    ],
    "labels_url": "https://api.github.com/repos/flutter/flutter-intellij/issues/2647/labels{/name}",
    "locked": false,
    "milestone": {
        "closed_at": null,
        "closed_issues": 428,
        "created_at": "2016-11-02T16:50:37Z",
        "creator": {
            "avatar_url": "https://avatars.githubusercontent.com/u/67586?v=4",
            "events_url": "https://api.github.com/users/pq/events{/privacy}",
            "followers_url": "https://api.github.com/users/pq/followers",
            "following_url": "https://api.github.com/users/pq/following{/other_user}",
            "gists_url": "https://api.github.com/users/pq/gists{/gist_id}",
            "gravatar_id": "",
            "html_url": "https://github.com/pq",
            "id": 67586,
            "login": "pq",
            "node_id": "MDQ6VXNlcjY3NTg2",
            "organizations_url": "https://api.github.com/users/pq/orgs",
            "received_events_url": "https://api.github.com/users/pq/received_events",
            "repos_url": "https://api.github.com/users/pq/repos",
            "site_admin": false,
            "starred_url": "https://api.github.com/users/pq/starred{/owner}{/repo}",
            "subscriptions_url": "https://api.github.com/users/pq/subscriptions",
            "type": "User",
            "url": "https://api.github.com/users/pq"
        },
        "description": "Issues under consideration for upcoming milestones. ",
        "due_on": null,
        "html_url": "https://github.com/flutter/flutter-intellij/milestone/11",
        "id": 2110124,
        "labels_url": "https://api.github.com/repos/flutter/flutter-intellij/milestones/11/labels",
        "node_id": "MDk6TWlsZXN0b25lMjExMDEyNA==",
        "number": 11,
        "open_issues": 251,
        "state": "open",
        "title": "On Deck",
        "updated_at": "2022-09-30T16:42:45Z",
        "url": "https://api.github.com/repos/flutter/flutter-intellij/milestones/11"
    },
    "node_id": "MDU6SXNzdWUzNjU2Nzk1NTA=",
    "number": 2647,
    "performed_via_github_app": null,
    "reactions": {
        "+1": 0,
        "-1": 0,
        "confused": 0,
        "eyes": 0,
        "heart": 0,
        "hooray": 0,
        "laugh": 0,
        "rocket": 0,
        "total_count": 0,
        "url": "https://api.github.com/repos/flutter/flutter-intellij/issues/2647/reactions"
    },
    "repository_url": "https://api.github.com/repos/flutter/flutter-intellij",
    "state": "closed",
    "state_reason": "completed",
    "timeline_url": "https://api.github.com/repos/flutter/flutter-intellij/issues/2647/timeline",
    "title": "Evaluating an expression @ a breakpoint causes analysis to fall down.",
    "updated_at": "2018-10-02T18:08:53Z",
    "url": "https://api.github.com/repos/flutter/flutter-intellij/issues/2647",
    "user": {
        "avatar_url": "https://avatars.githubusercontent.com/u/67586?v=4",
        "events_url": "https://api.github.com/users/pq/events{/privacy}",
        "followers_url": "https://api.github.com/users/pq/followers",
        "following_url": "https://api.github.com/users/pq/following{/other_user}",
        "gists_url": "https://api.github.com/users/pq/gists{/gist_id}",
        "gravatar_id": "",
        "html_url": "https://github.com/pq",
        "id": 67586,
        "login": "pq",
        "node_id": "MDQ6VXNlcjY3NTg2",
        "organizations_url": "https://api.github.com/users/pq/orgs",
        "received_events_url": "https://api.github.com/users/pq/received_events",
        "repos_url": "https://api.github.com/users/pq/repos",
        "site_admin": false,
        "starred_url": "https://api.github.com/users/pq/starred{/owner}{/repo}",
        "subscriptions_url": "https://api.github.com/users/pq/subscriptions",
        "type": "User",
        "url": "https://api.github.com/users/pq"
    }
}