{
    "active_lock_reason": null,
    "assignee": {
        "avatar_url": "https://avatars.githubusercontent.com/u/1269969?v=4",
        "events_url": "https://api.github.com/users/devoncarew/events{/privacy}",
        "followers_url": "https://api.github.com/users/devoncarew/followers",
        "following_url": "https://api.github.com/users/devoncarew/following{/other_user}",
        "gists_url": "https://api.github.com/users/devoncarew/gists{/gist_id}",
        "gravatar_id": "",
        "html_url": "https://github.com/devoncarew",
        "id": 1269969,
        "login": "devoncarew",
        "node_id": "MDQ6VXNlcjEyNjk5Njk=",
        "organizations_url": "https://api.github.com/users/devoncarew/orgs",
        "received_events_url": "https://api.github.com/users/devoncarew/received_events",
        "repos_url": "https://api.github.com/users/devoncarew/repos",
        "site_admin": false,
        "starred_url": "https://api.github.com/users/devoncarew/starred{/owner}{/repo}",
        "subscriptions_url": "https://api.github.com/users/devoncarew/subscriptions",
        "type": "User",
        "url": "https://api.github.com/users/devoncarew"
    },
    "assignees": [
        {
            "avatar_url": "https://avatars.githubusercontent.com/u/1269969?v=4",
            "events_url": "https://api.github.com/users/devoncarew/events{/privacy}",
            "followers_url": "https://api.github.com/users/devoncarew/followers",
            "following_url": "https://api.github.com/users/devoncarew/following{/other_user}",
            "gists_url": "https://api.github.com/users/devoncarew/gists{/gist_id}",
            "gravatar_id": "",
            "html_url": "https://github.com/devoncarew",
            "id": 1269969,
            "login": "devoncarew",
            "node_id": "MDQ6VXNlcjEyNjk5Njk=",
            "organizations_url": "https://api.github.com/users/devoncarew/orgs",
            "received_events_url": "https://api.github.com/users/devoncarew/received_events",
            "repos_url": "https://api.github.com/users/devoncarew/repos",
            "site_admin": false,
            "starred_url": "https://api.github.com/users/devoncarew/starred{/owner}{/repo}",
            "subscriptions_url": "https://api.github.com/users/devoncarew/subscriptions",
            "type": "User",
            "url": "https://api.github.com/users/devoncarew"
        }
    ],
    "author_association": "CONTRIBUTOR",
    "body": "1. Introduce an error to test code (say a line that has no semicolon).\r\n2. Run the app\r\n3. Reloading the app fails.\r\n\r\nThe lines below cause this to happen:\r\nhttps://github.com/flutter/flutter-intellij/blob/a1748e99fd093697946b4cbbfa975bc33cc57d52/src/io/flutter/run/FlutterReloadManager.java#L199-L205\r\n\r\nI'm looking into removing those and letting the flutter daemon tell us if it's safe to reload the app.  The parent to this issue is https://github.com/flutter/flutter/issues/27618",
    "closed_at": "2020-01-25T03:37:26Z",
    "comment_data": [
        {
            "author_association": "MEMBER",
            "body": "We should consider removing the check for analysis errors before performing a reload on save.",
            "created_at": "2020-01-07T20:31:51Z",
            "html_url": "https://github.com/flutter/flutter-intellij/issues/3168#issuecomment-571758481",
            "id": 571758481,
            "issue_url": "https://api.github.com/repos/flutter/flutter-intellij/issues/3168",
            "node_id": "MDEyOklzc3VlQ29tbWVudDU3MTc1ODQ4MQ==",
            "performed_via_github_app": null,
            "reactions": {
                "+1": 0,
                "-1": 0,
                "confused": 0,
                "eyes": 0,
                "heart": 0,
                "hooray": 0,
                "laugh": 0,
                "rocket": 0,
                "total_count": 0,
                "url": "https://api.github.com/repos/flutter/flutter-intellij/issues/comments/571758481/reactions"
            },
            "updated_at": "2020-01-07T20:31:51Z",
            "url": "https://api.github.com/repos/flutter/flutter-intellij/issues/comments/571758481",
            "user": {
                "avatar_url": "https://avatars.githubusercontent.com/u/1269969?v=4",
                "events_url": "https://api.github.com/users/devoncarew/events{/privacy}",
                "followers_url": "https://api.github.com/users/devoncarew/followers",
                "following_url": "https://api.github.com/users/devoncarew/following{/other_user}",
                "gists_url": "https://api.github.com/users/devoncarew/gists{/gist_id}",
                "gravatar_id": "",
                "html_url": "https://github.com/devoncarew",
                "id": 1269969,
                "login": "devoncarew",
                "node_id": "MDQ6VXNlcjEyNjk5Njk=",
                "organizations_url": "https://api.github.com/users/devoncarew/orgs",
                "received_events_url": "https://api.github.com/users/devoncarew/received_events",
                "repos_url": "https://api.github.com/users/devoncarew/repos",
                "site_admin": false,
                "starred_url": "https://api.github.com/users/devoncarew/starred{/owner}{/repo}",
                "subscriptions_url": "https://api.github.com/users/devoncarew/subscriptions",
                "type": "User",
                "url": "https://api.github.com/users/devoncarew"
            }
        },
        {
            "author_association": "MEMBER",
            "body": "fixed by https://github.com/flutter/flutter-intellij/pull/4327",
            "created_at": "2020-01-25T03:37:26Z",
            "html_url": "https://github.com/flutter/flutter-intellij/issues/3168#issuecomment-578373068",
            "id": 578373068,
            "issue_url": "https://api.github.com/repos/flutter/flutter-intellij/issues/3168",
            "node_id": "MDEyOklzc3VlQ29tbWVudDU3ODM3MzA2OA==",
            "performed_via_github_app": null,
            "reactions": {
                "+1": 0,
                "-1": 0,
                "confused": 0,
                "eyes": 0,
                "heart": 0,
                "hooray": 0,
                "laugh": 0,
                "rocket": 0,
                "total_count": 0,
                "url": "https://api.github.com/repos/flutter/flutter-intellij/issues/comments/578373068/reactions"
            },
            "updated_at": "2020-01-25T03:37:26Z",
            "url": "https://api.github.com/repos/flutter/flutter-intellij/issues/comments/578373068",
            "user": {
                "avatar_url": "https://avatars.githubusercontent.com/u/1269969?v=4",
                "events_url": "https://api.github.com/users/devoncarew/events{/privacy}",
                "followers_url": "https://api.github.com/users/devoncarew/followers",
                "following_url": "https://api.github.com/users/devoncarew/following{/other_user}",
                "gists_url": "https://api.github.com/users/devoncarew/gists{/gist_id}",
                "gravatar_id": "",
                "html_url": "https://github.com/devoncarew",
                "id": 1269969,
                "login": "devoncarew",
                "node_id": "MDQ6VXNlcjEyNjk5Njk=",
                "organizations_url": "https://api.github.com/users/devoncarew/orgs",
                "received_events_url": "https://api.github.com/users/devoncarew/received_events",
                "repos_url": "https://api.github.com/users/devoncarew/repos",
                "site_admin": false,
                "starred_url": "https://api.github.com/users/devoncarew/starred{/owner}{/repo}",
                "subscriptions_url": "https://api.github.com/users/devoncarew/subscriptions",
                "type": "User",
                "url": "https://api.github.com/users/devoncarew"
            }
        }
    ],
    "comments": 2,
    "comments_url": "https://api.github.com/repos/flutter/flutter-intellij/issues/3168/comments",
    "created_at": "2019-02-06T22:20:04Z",
    "event_data": [
        {
            "actor": {
                "avatar_url": "https://avatars.githubusercontent.com/u/14947366?v=4",
                "events_url": "https://api.github.com/users/DaveShuckerow/events{/privacy}",
                "followers_url": "https://api.github.com/users/DaveShuckerow/followers",
                "following_url": "https://api.github.com/users/DaveShuckerow/following{/other_user}",
                "gists_url": "https://api.github.com/users/DaveShuckerow/gists{/gist_id}",
                "gravatar_id": "",
                "html_url": "https://github.com/DaveShuckerow",
                "id": 14947366,
                "login": "DaveShuckerow",
                "node_id": "MDQ6VXNlcjE0OTQ3MzY2",
                "organizations_url": "https://api.github.com/users/DaveShuckerow/orgs",
                "received_events_url": "https://api.github.com/users/DaveShuckerow/received_events",
                "repos_url": "https://api.github.com/users/DaveShuckerow/repos",
                "site_admin": false,
                "starred_url": "https://api.github.com/users/DaveShuckerow/starred{/owner}{/repo}",
                "subscriptions_url": "https://api.github.com/users/DaveShuckerow/subscriptions",
                "type": "User",
                "url": "https://api.github.com/users/DaveShuckerow"
            },
            "commit_id": null,
            "commit_url": null,
            "created_at": "2019-02-06T22:20:04Z",
            "event": "labeled",
            "id": 2122603062,
            "label": {
                "color": "f74c7f",
                "name": "reload"
            },
            "node_id": "MDEyOkxhYmVsZWRFdmVudDIxMjI2MDMwNjI=",
            "performed_via_github_app": null,
            "url": "https://api.github.com/repos/flutter/flutter-intellij/issues/events/2122603062"
        },
        {
            "actor": {
                "avatar_url": "https://avatars.githubusercontent.com/u/43759233?v=4",
                "events_url": "https://api.github.com/users/kenzieschmoll/events{/privacy}",
                "followers_url": "https://api.github.com/users/kenzieschmoll/followers",
                "following_url": "https://api.github.com/users/kenzieschmoll/following{/other_user}",
                "gists_url": "https://api.github.com/users/kenzieschmoll/gists{/gist_id}",
                "gravatar_id": "",
                "html_url": "https://github.com/kenzieschmoll",
                "id": 43759233,
                "login": "kenzieschmoll",
                "node_id": "MDQ6VXNlcjQzNzU5MjMz",
                "organizations_url": "https://api.github.com/users/kenzieschmoll/orgs",
                "received_events_url": "https://api.github.com/users/kenzieschmoll/received_events",
                "repos_url": "https://api.github.com/users/kenzieschmoll/repos",
                "site_admin": false,
                "starred_url": "https://api.github.com/users/kenzieschmoll/starred{/owner}{/repo}",
                "subscriptions_url": "https://api.github.com/users/kenzieschmoll/subscriptions",
                "type": "User",
                "url": "https://api.github.com/users/kenzieschmoll"
            },
            "commit_id": null,
            "commit_url": null,
            "created_at": "2019-02-06T22:49:12Z",
            "event": "milestoned",
            "id": 2122661712,
            "milestone": {
                "title": "M33"
            },
            "node_id": "MDE1Ok1pbGVzdG9uZWRFdmVudDIxMjI2NjE3MTI=",
            "performed_via_github_app": null,
            "url": "https://api.github.com/repos/flutter/flutter-intellij/issues/events/2122661712"
        },
        {
            "actor": {
                "avatar_url": "https://avatars.githubusercontent.com/u/1269969?v=4",
                "events_url": "https://api.github.com/users/devoncarew/events{/privacy}",
                "followers_url": "https://api.github.com/users/devoncarew/followers",
                "following_url": "https://api.github.com/users/devoncarew/following{/other_user}",
                "gists_url": "https://api.github.com/users/devoncarew/gists{/gist_id}",
                "gravatar_id": "",
                "html_url": "https://github.com/devoncarew",
                "id": 1269969,
                "login": "devoncarew",
                "node_id": "MDQ6VXNlcjEyNjk5Njk=",
                "organizations_url": "https://api.github.com/users/devoncarew/orgs",
                "received_events_url": "https://api.github.com/users/devoncarew/received_events",
                "repos_url": "https://api.github.com/users/devoncarew/repos",
                "site_admin": false,
                "starred_url": "https://api.github.com/users/devoncarew/starred{/owner}{/repo}",
                "subscriptions_url": "https://api.github.com/users/devoncarew/subscriptions",
                "type": "User",
                "url": "https://api.github.com/users/devoncarew"
            },
            "commit_id": null,
            "commit_url": null,
            "created_at": "2019-02-11T18:27:41Z",
            "event": "demilestoned",
            "id": 2131408237,
            "milestone": {
                "title": "M33"
            },
            "node_id": "MDE3OkRlbWlsZXN0b25lZEV2ZW50MjEzMTQwODIzNw==",
            "performed_via_github_app": null,
            "url": "https://api.github.com/repos/flutter/flutter-intellij/issues/events/2131408237"
        },
        {
            "actor": {
                "avatar_url": "https://avatars.githubusercontent.com/u/1269969?v=4",
                "events_url": "https://api.github.com/users/devoncarew/events{/privacy}",
                "followers_url": "https://api.github.com/users/devoncarew/followers",
                "following_url": "https://api.github.com/users/devoncarew/following{/other_user}",
                "gists_url": "https://api.github.com/users/devoncarew/gists{/gist_id}",
                "gravatar_id": "",
                "html_url": "https://github.com/devoncarew",
                "id": 1269969,
                "login": "devoncarew",
                "node_id": "MDQ6VXNlcjEyNjk5Njk=",
                "organizations_url": "https://api.github.com/users/devoncarew/orgs",
                "received_events_url": "https://api.github.com/users/devoncarew/received_events",
                "repos_url": "https://api.github.com/users/devoncarew/repos",
                "site_admin": false,
                "starred_url": "https://api.github.com/users/devoncarew/starred{/owner}{/repo}",
                "subscriptions_url": "https://api.github.com/users/devoncarew/subscriptions",
                "type": "User",
                "url": "https://api.github.com/users/devoncarew"
            },
            "commit_id": null,
            "commit_url": null,
            "created_at": "2019-02-11T18:27:41Z",
            "event": "milestoned",
            "id": 2131408238,
            "milestone": {
                "title": "On Deck"
            },
            "node_id": "MDE1Ok1pbGVzdG9uZWRFdmVudDIxMzE0MDgyMzg=",
            "performed_via_github_app": null,
            "url": "https://api.github.com/repos/flutter/flutter-intellij/issues/events/2131408238"
        },
        {
            "actor": {
                "avatar_url": "https://avatars.githubusercontent.com/u/1269969?v=4",
                "events_url": "https://api.github.com/users/devoncarew/events{/privacy}",
                "followers_url": "https://api.github.com/users/devoncarew/followers",
                "following_url": "https://api.github.com/users/devoncarew/following{/other_user}",
                "gists_url": "https://api.github.com/users/devoncarew/gists{/gist_id}",
                "gravatar_id": "",
                "html_url": "https://github.com/devoncarew",
                "id": 1269969,
                "login": "devoncarew",
                "node_id": "MDQ6VXNlcjEyNjk5Njk=",
                "organizations_url": "https://api.github.com/users/devoncarew/orgs",
                "received_events_url": "https://api.github.com/users/devoncarew/received_events",
                "repos_url": "https://api.github.com/users/devoncarew/repos",
                "site_admin": false,
                "starred_url": "https://api.github.com/users/devoncarew/starred{/owner}{/repo}",
                "subscriptions_url": "https://api.github.com/users/devoncarew/subscriptions",
                "type": "User",
                "url": "https://api.github.com/users/devoncarew"
            },
            "commit_id": null,
            "commit_url": null,
            "created_at": "2020-01-07T20:31:22Z",
            "event": "demilestoned",
            "id": 2928961192,
            "milestone": {
                "title": "On Deck"
            },
            "node_id": "MDE3OkRlbWlsZXN0b25lZEV2ZW50MjkyODk2MTE5Mg==",
            "performed_via_github_app": null,
            "url": "https://api.github.com/repos/flutter/flutter-intellij/issues/events/2928961192"
        },
        {
            "actor": {
                "avatar_url": "https://avatars.githubusercontent.com/u/1269969?v=4",
                "events_url": "https://api.github.com/users/devoncarew/events{/privacy}",
                "followers_url": "https://api.github.com/users/devoncarew/followers",
                "following_url": "https://api.github.com/users/devoncarew/following{/other_user}",
                "gists_url": "https://api.github.com/users/devoncarew/gists{/gist_id}",
                "gravatar_id": "",
                "html_url": "https://github.com/devoncarew",
                "id": 1269969,
                "login": "devoncarew",
                "node_id": "MDQ6VXNlcjEyNjk5Njk=",
                "organizations_url": "https://api.github.com/users/devoncarew/orgs",
                "received_events_url": "https://api.github.com/users/devoncarew/received_events",
                "repos_url": "https://api.github.com/users/devoncarew/repos",
                "site_admin": false,
                "starred_url": "https://api.github.com/users/devoncarew/starred{/owner}{/repo}",
                "subscriptions_url": "https://api.github.com/users/devoncarew/subscriptions",
                "type": "User",
                "url": "https://api.github.com/users/devoncarew"
            },
            "commit_id": null,
            "commit_url": null,
            "created_at": "2020-01-07T20:31:22Z",
            "event": "milestoned",
            "id": 2928961194,
            "milestone": {
                "title": "M43"
            },
            "node_id": "MDE1Ok1pbGVzdG9uZWRFdmVudDI5Mjg5NjExOTQ=",
            "performed_via_github_app": null,
            "url": "https://api.github.com/repos/flutter/flutter-intellij/issues/events/2928961194"
        },
        {
            "actor": {
                "avatar_url": "https://avatars.githubusercontent.com/u/1269969?v=4",
                "events_url": "https://api.github.com/users/devoncarew/events{/privacy}",
                "followers_url": "https://api.github.com/users/devoncarew/followers",
                "following_url": "https://api.github.com/users/devoncarew/following{/other_user}",
                "gists_url": "https://api.github.com/users/devoncarew/gists{/gist_id}",
                "gravatar_id": "",
                "html_url": "https://github.com/devoncarew",
                "id": 1269969,
                "login": "devoncarew",
                "node_id": "MDQ6VXNlcjEyNjk5Njk=",
                "organizations_url": "https://api.github.com/users/devoncarew/orgs",
                "received_events_url": "https://api.github.com/users/devoncarew/received_events",
                "repos_url": "https://api.github.com/users/devoncarew/repos",
                "site_admin": false,
                "starred_url": "https://api.github.com/users/devoncarew/starred{/owner}{/repo}",
                "subscriptions_url": "https://api.github.com/users/devoncarew/subscriptions",
                "type": "User",
                "url": "https://api.github.com/users/devoncarew"
            },
            "assignee": {
                "avatar_url": "https://avatars.githubusercontent.com/u/1269969?v=4",
                "events_url": "https://api.github.com/users/devoncarew/events{/privacy}",
                "followers_url": "https://api.github.com/users/devoncarew/followers",
                "following_url": "https://api.github.com/users/devoncarew/following{/other_user}",
                "gists_url": "https://api.github.com/users/devoncarew/gists{/gist_id}",
                "gravatar_id": "",
                "html_url": "https://github.com/devoncarew",
                "id": 1269969,
                "login": "devoncarew",
                "node_id": "MDQ6VXNlcjEyNjk5Njk=",
                "organizations_url": "https://api.github.com/users/devoncarew/orgs",
                "received_events_url": "https://api.github.com/users/devoncarew/received_events",
                "repos_url": "https://api.github.com/users/devoncarew/repos",
                "site_admin": false,
                "starred_url": "https://api.github.com/users/devoncarew/starred{/owner}{/repo}",
                "subscriptions_url": "https://api.github.com/users/devoncarew/subscriptions",
                "type": "User",
                "url": "https://api.github.com/users/devoncarew"
            },
            "assigner": {
                "avatar_url": "https://avatars.githubusercontent.com/u/1269969?v=4",
                "events_url": "https://api.github.com/users/devoncarew/events{/privacy}",
                "followers_url": "https://api.github.com/users/devoncarew/followers",
                "following_url": "https://api.github.com/users/devoncarew/following{/other_user}",
                "gists_url": "https://api.github.com/users/devoncarew/gists{/gist_id}",
                "gravatar_id": "",
                "html_url": "https://github.com/devoncarew",
                "id": 1269969,
                "login": "devoncarew",
                "node_id": "MDQ6VXNlcjEyNjk5Njk=",
                "organizations_url": "https://api.github.com/users/devoncarew/orgs",
                "received_events_url": "https://api.github.com/users/devoncarew/received_events",
                "repos_url": "https://api.github.com/users/devoncarew/repos",
                "site_admin": false,
                "starred_url": "https://api.github.com/users/devoncarew/starred{/owner}{/repo}",
                "subscriptions_url": "https://api.github.com/users/devoncarew/subscriptions",
                "type": "User",
                "url": "https://api.github.com/users/devoncarew"
            },
            "commit_id": null,
            "commit_url": null,
            "created_at": "2020-01-23T17:36:06Z",
            "event": "assigned",
            "id": 2974633274,
            "node_id": "MDEzOkFzc2lnbmVkRXZlbnQyOTc0NjMzMjc0",
            "performed_via_github_app": null,
            "url": "https://api.github.com/repos/flutter/flutter-intellij/issues/events/2974633274"
        },
        {
            "actor": {
                "avatar_url": "https://avatars.githubusercontent.com/u/1269969?v=4",
                "events_url": "https://api.github.com/users/devoncarew/events{/privacy}",
                "followers_url": "https://api.github.com/users/devoncarew/followers",
                "following_url": "https://api.github.com/users/devoncarew/following{/other_user}",
                "gists_url": "https://api.github.com/users/devoncarew/gists{/gist_id}",
                "gravatar_id": "",
                "html_url": "https://github.com/devoncarew",
                "id": 1269969,
                "login": "devoncarew",
                "node_id": "MDQ6VXNlcjEyNjk5Njk=",
                "organizations_url": "https://api.github.com/users/devoncarew/orgs",
                "received_events_url": "https://api.github.com/users/devoncarew/received_events",
                "repos_url": "https://api.github.com/users/devoncarew/repos",
                "site_admin": false,
                "starred_url": "https://api.github.com/users/devoncarew/starred{/owner}{/repo}",
                "subscriptions_url": "https://api.github.com/users/devoncarew/subscriptions",
                "type": "User",
                "url": "https://api.github.com/users/devoncarew"
            },
            "commit_id": null,
            "commit_url": null,
            "created_at": "2020-01-25T03:37:26Z",
            "event": "closed",
            "id": 2979091841,
            "node_id": "MDExOkNsb3NlZEV2ZW50Mjk3OTA5MTg0MQ==",
            "performed_via_github_app": null,
            "state_reason": null,
            "url": "https://api.github.com/repos/flutter/flutter-intellij/issues/events/2979091841"
        }
    ],
    "events_url": "https://api.github.com/repos/flutter/flutter-intellij/issues/3168/events",
    "html_url": "https://github.com/flutter/flutter-intellij/issues/3168",
    "id": 407457511,
    "labels": [
        {
            "color": "f74c7f",
            "default": false,
            "description": null,
            "id": 821691811,
            "name": "reload",
            "node_id": "MDU6TGFiZWw4MjE2OTE4MTE=",
            "url": "https://api.github.com/repos/flutter/flutter-intellij/labels/reload"
        }
    ],
    "labels_url": "https://api.github.com/repos/flutter/flutter-intellij/issues/3168/labels{/name}",
    "locked": false,
    "milestone": {
        "closed_at": "2020-02-10T22:32:52Z",
        "closed_issues": 29,
        "created_at": "2019-11-19T16:29:14Z",
        "creator": {
            "avatar_url": "https://avatars.githubusercontent.com/u/1269969?v=4",
            "events_url": "https://api.github.com/users/devoncarew/events{/privacy}",
            "followers_url": "https://api.github.com/users/devoncarew/followers",
            "following_url": "https://api.github.com/users/devoncarew/following{/other_user}",
            "gists_url": "https://api.github.com/users/devoncarew/gists{/gist_id}",
            "gravatar_id": "",
            "html_url": "https://github.com/devoncarew",
            "id": 1269969,
            "login": "devoncarew",
            "node_id": "MDQ6VXNlcjEyNjk5Njk=",
            "organizations_url": "https://api.github.com/users/devoncarew/orgs",
            "received_events_url": "https://api.github.com/users/devoncarew/received_events",
            "repos_url": "https://api.github.com/users/devoncarew/repos",
            "site_admin": false,
            "starred_url": "https://api.github.com/users/devoncarew/starred{/owner}{/repo}",
            "subscriptions_url": "https://api.github.com/users/devoncarew/subscriptions",
            "type": "User",
            "url": "https://api.github.com/users/devoncarew"
        },
        "description": "",
        "due_on": "2020-01-31T08:00:00Z",
        "html_url": "https://github.com/flutter/flutter-intellij/milestone/54",
        "id": 4860237,
        "labels_url": "https://api.github.com/repos/flutter/flutter-intellij/milestones/54/labels",
        "node_id": "MDk6TWlsZXN0b25lNDg2MDIzNw==",
        "number": 54,
        "open_issues": 0,
        "state": "closed",
        "title": "M43",
        "updated_at": "2020-02-10T22:32:52Z",
        "url": "https://api.github.com/repos/flutter/flutter-intellij/milestones/54"
    },
    "node_id": "MDU6SXNzdWU0MDc0NTc1MTE=",
    "number": 3168,
    "performed_via_github_app": null,
    "reactions": {
        "+1": 0,
        "-1": 0,
        "confused": 0,
        "eyes": 0,
        "heart": 0,
        "hooray": 0,
        "laugh": 0,
        "rocket": 0,
        "total_count": 0,
        "url": "https://api.github.com/repos/flutter/flutter-intellij/issues/3168/reactions"
    },
    "repository_url": "https://api.github.com/repos/flutter/flutter-intellij",
    "state": "closed",
    "state_reason": "completed",
    "timeline_url": "https://api.github.com/repos/flutter/flutter-intellij/issues/3168/timeline",
    "title": "Error check before hot reload will cause reloads to fail if a clean app is in a bigger project with separate failures",
    "updated_at": "2020-01-25T03:37:27Z",
    "url": "https://api.github.com/repos/flutter/flutter-intellij/issues/3168",
    "user": {
        "avatar_url": "https://avatars.githubusercontent.com/u/14947366?v=4",
        "events_url": "https://api.github.com/users/DaveShuckerow/events{/privacy}",
        "followers_url": "https://api.github.com/users/DaveShuckerow/followers",
        "following_url": "https://api.github.com/users/DaveShuckerow/following{/other_user}",
        "gists_url": "https://api.github.com/users/DaveShuckerow/gists{/gist_id}",
        "gravatar_id": "",
        "html_url": "https://github.com/DaveShuckerow",
        "id": 14947366,
        "login": "DaveShuckerow",
        "node_id": "MDQ6VXNlcjE0OTQ3MzY2",
        "organizations_url": "https://api.github.com/users/DaveShuckerow/orgs",
        "received_events_url": "https://api.github.com/users/DaveShuckerow/received_events",
        "repos_url": "https://api.github.com/users/DaveShuckerow/repos",
        "site_admin": false,
        "starred_url": "https://api.github.com/users/DaveShuckerow/starred{/owner}{/repo}",
        "subscriptions_url": "https://api.github.com/users/DaveShuckerow/subscriptions",
        "type": "User",
        "url": "https://api.github.com/users/DaveShuckerow"
    }
}